[
	{
		"Title": "Persona 3: #1 Spring of Birth",
		"Subtitle": "",
		"Summary": "",
		"Description": "Der junge Makoto zieht in die Stadt Iwatodai, wo sich seltsame Dinge ereignen: Als er um Mitternacht mit dem Zug ankommt, verwandeln sich in der sogenannten Dunklen Stunde die Einwohner der Stadt plötzlich in Särge. Im Wohnheim der Gekkoukan Highschool wartet derweil bereits ein Junge mit einem seltsamen Vertrag auf ihn. Bei einem Kampf gegen eine riesige Kreatur wird Makoto plötzlich zu Persona und entdeckt ungeahnte Fähigkeiten.",
		"ChannelName": "ProSieben MAXX",
		"Start": "2018-09-12T00:02:14+02:00",
		"Stop": "2018-09-12T01:45:52+02:00",
		"Info": {}
	},
	{
		"Title": "Conan",
		"Subtitle": "",
		"Summary": "",
		"Description": "Der Koloss Jason Moma schwingt das Schwert: Von klein auf ist es Conan gewohnt, zu kämpfen. Als jedoch das Heimatdorf des imposanten Kriegers aus der mythischen Welt Hyboria überfallen wird, ist er außer Stande, seinem Vater das Leben zu retten. Dessen Mörder Khalar Zym plant, mithilfe einer legendären Maske über Hyboria zu herrschen. Conan will ihm einen Strich durch die Rechnung machen und Rache üben. Dabei braucht er die Hilfe der jungen Nonne Tamara.\n\nRegie: Marcus Nispel\nDrehbuch: Thomas Dean Donnelly, Joshua Oppenheimer, Sean Hood\nKomponist: Tyler Bates\nKamera: Thomas Kloss\nSchnitt: Ken Blackwell\n\nDarsteller:\nJason Momoa (Conan)\nRose McGowan (Marique)\nRon Perlman (Corin)\nStephen Lang (Khalar Zym)\nRachel Nichols (Tamara)\nBob Sapp (Ukafa)\nSteven O'Donnell (Lucius)\nRaad Rawi (Fassir)\nLaila Rouass (Fialla)",
		"ChannelName": "ProSieben MAXX",
		"Start": "2018-09-12T01:45:52+02:00",
		"Stop": "2018-09-12T03:26:48+02:00",
		"Info": {
			"Kamera": [
				"Thomas Kloss"
			],
			"Komponist": [
				"Tyler Bates"
			],
			"Regie": [
				"Marcus Nispel"
			],
			"Schnitt": [
				"Ken Blackwell"
			]
		}
	},
	{
		"Title": "Terra Nova",
		"Subtitle": "",
		"Summary": "",
		"Description": "In der Nähe von Terra Nova explodiert ein Meteorit. In Terra Nova fällt daraufhin die Stromversorgung aus, sämtliche Schaltelemente und Mikrochips sind zerstört. Da auch das Abwehrsystem der Kolonie defekt ist, sind die Menschen Angriffen der Sixer und Raubtier-Attacken hilflos ausgeliefert. Commander Taylor bittet Boylan, einen ehemaligen Munitionsoffizier, um Hilfe. Die Zeit drängt, als ein weiterer Meteoriteneinschlag eine Druckwelle auslöst ...\n\nRegie: Jon Cassar\nDrehbuch: Terry Matalas, Travis Fickett\nKomponist: Brian Tyler\nKamera: Jeffrey C. Mygatt\nSchnitt: John Peter Bernardo\n\nDarsteller:\nJason O'Mara (Jim Shannon)\nShelley Conn (Dr. Elisabeth Shannon)\nStephen Lang (Commander Nathaniel Taylor)\nDamien Garvey (Tom Boylan)\nChristine Adams (Mira)\nAllison Miller (Skye)\nLandon Liboiron (Josh Shannon)\nNaomi Scott (Maddy Shannon)\nRod Hallett (Dr. Malcolm Wallace)",
		"ChannelName": "ProSieben MAXX",
		"Start": "2018-09-12T03:26:48+02:00",
		"Stop": "2018-09-12T04:08:09+02:00",
		"Info": {
			"Drehbuch": [
				"Terry Matalas",
				"Travis Fickett"
			],
			"Kamera": [
				"Jeffrey C. Mygatt"
			],
			"Komponist": [
				"Brian Tyler"
			],
			"Regie": [
				"Jon Cassar"
			],
			"Schnitt": [
				"John Peter Bernardo"
			]
		}
	},
	{
		"Title": "Terra Nova",
		"Subtitle": "",
		"Summary": "",
		"Description": "Josh soll für Mira ins Krankenhaus einbrechen und ein Medikament klauen. Im Gegenzug ist Mira dazu bereit, Joshs Freundin Kara aus der alten Welt nach Terra Nova zu schleusen. Der Plan misslingt jedoch ... Derweil ist Dr. Horton, ein berühmter Wissenschaftler, nach einer längeren Expedition zurück in Terra Nova - er wird freudig empfangen. Allerdings verhält sich Horton merkwürdig, und Maddy vermutet, dass es sich gar nicht um den echten Dr. Horton handelt.\n\nRegie: Bryan Spicer\nDrehbuch: David Graziano, Brynn Malone\nKomponist: Brian Tyler\nKamera: Jeffrey C. Mygatt\nSchnitt: Donn Aron\n\nDarsteller:\nJason O'Mara (Jim Shannon)\nShelley Conn (Dr. Elisabeth Shannon)\nNaomi Scott (Maddy Shannon)\nStephen Lang (Commander Nathaniel Taylor)\nChristine Adams (Mira)\nLandon Liboiron (Josh Shannon)\nRobert Coleby (Ken Horton / Andrew Fickett)\nDamien Garvey (Tom Boylan)\nRod Hallett (Dr. Malcolm Wallace)",
		"ChannelName": "ProSieben MAXX",
		"Start": "2018-09-12T04:08:09+02:00",
		"Stop": "2018-09-12T04:49:28+02:00",
		"Info": {
			"Drehbuch": [
				"David Graziano",
				"Brynn Malone"
			],
			"Kamera": [
				"Jeffrey C. Mygatt"
			],
			"Komponist": [
				"Brian Tyler"
			],
			"Regie": [
				"Bryan Spicer"
			],
			"Schnitt": [
				"Donn Aron"
			]
		}
	},
	{
		"Title": "Terra Nova",
		"Subtitle": "",
		"Summary": "",
		"Description": "Mira und ihre Leute greifen einen Versorgungstrupp an und erbeuten Waffen, Medikamente und Ausrüstung. Es scheint, als gäbe es einen Spion, der Mira mit Informationen beliefert. Indes steht Terra Nova wegen des Erntedankfestes Kopf. Als ein Soldat versehentlich eine Libelle, die bei den Vorbereitungen über den Marktplatz fliegt, verletzt, stellt sich heraus, dass sie einen Mikrochip bei sich trägt. Sie ist eine Art Brieftaube, durch die Mira mit dem Spion in Verbindung bleibt.\n\nRegie: Bryan Spicer\nDrehbuch: Jose Molina\nKomponist: Brian Tyler\nKamera: Jeffrey C. Mygatt\nSchnitt: Donn Aron, Michael O'Halloran\n\nDarsteller:\nJason O'Mara (Jim Shannon)\nShelley Conn (Dr. Elisabeth Shannon)\nChristine Adams (Mira)\nStephen Lang (Commander Nathaniel Taylor)\nAllison Miller (Skye)\nLandon Liboiron (Josh Shannon)\nNaomi Scott (Maddy Shannon)\nRod Hallett (Dr. Malcolm Wallace)\nSimone Kessell (Lt. Alicia Washington)",
		"ChannelName": "ProSieben MAXX",
		"Start": "2018-09-12T04:49:28+02:00",
		"Stop": "2018-09-12T05:29:07+02:00",
		"Info": {
			"Drehbuch": [
				"Jose Molina"
			],
			"Kamera": [
				"Jeffrey C. Mygatt"
			],
			"Komponist": [
				"Brian Tyler"
			],
			"Regie": [
				"Bryan Spicer"
			],
			"Schnitt": [
				"Donn Aron",
				"Michael O'Halloran"
			]
		}
	},
	{
		"Title": "Terra Nova",
		"Subtitle": "",
		"Summary": "",
		"Description": "Taylor sucht im Dschungel nach seinem Sohn Lucas. Er überträgt für die Zeit seiner Abwesenheit das Kommando über die wegen des Spions abgeriegelte Kolonie an Jim. Jim hat mittlerweile Hinweise auf den Aufenthaltsort des Spions bekommen, doch als er mit Reynolds dort ankommt, ist der Spion spurlos verschwunden. Sie finden in einem Glas mit Farbversiegelung lediglich einen Blutstropfen. Jim bittet Elisabeth um eine DNA-Analyse, um festzustellen, von wem das Blut stammt ...\n\nRegie: Karen Gaviola\nDrehbuch: Paul Grellong\nKomponist: Brian Tyler\nKamera: Jeffrey C. Mygatt\nSchnitt: Michael N. Knue\n\nDarsteller:\nJason O'Mara (Jim Shannon)\nShelley Conn (Dr. Elisabeth Shannon)\nStephen Lang (Commander Nathaniel Taylor)\nDean Geyer (Mark Reynolds)\nAllison Miller (Skye)\nChristine Adams (Mira)\nLandon Liboiron (Josh Shannon)\nNaomi Scott (Maddy Shannon)\nRod Hallett (Dr. Malcolm Wallace)",
		"ChannelName": "ProSieben MAXX",
		"Start": "2018-09-12T05:29:07+02:00",
		"Stop": "2018-09-12T06:07:59+02:00",
		"Info": {
			"Drehbuch": [
				"Paul Grellong"
			],
			"Kamera": [
				"Jeffrey C. Mygatt"
			],
			"Komponist": [
				"Brian Tyler"
			],
			"Regie": [
				"Karen Gaviola"
			],
			"Schnitt": [
				"Michael N. Knue"
			]
		}
	},
	{
		"Title": "Galileo To Go",
		"Subtitle": "",
		"Summary": "",
		"Description": "\"Galileo to Go\" - die tägliche Portion Wissen für jedermann. Überraschende Einblicke zu den spannendsten Fragen des Alltags.",
		"ChannelName": "ProSieben MAXX",
		"Start": "2018-09-12T06:07:59+02:00",
		"Stop": "2018-09-12T06:20:36+02:00",
		"Info": {}
	},
	{
		"Title": "Ax Men - Die Holzfäller",
		"Subtitle": "",
		"Summary": "",
		"Description": "Shelbys Assistent wirft nach einem Unfall das Handtuch. Bei der Firma Big Gun muss dringend ein neuer Kranführer her: Das abschüssige Gelände erfordert ein besonderes Händchen.",
		"ChannelName": "ProSieben MAXX",
		"Start": "2018-09-12T06:20:36+02:00",
		"Stop": "2018-09-12T07:12:38+02:00",
		"Info": {}
	},
	{
		"Title": "Ax Men - Die Holzfäller",
		"Subtitle": "",
		"Summary": "",
		"Description": "Die Saison neigt sich dem Ende entgegen, und die Holfäller riskieren viel, um obenauf zu bleiben. Bei Rygaard setzen die Männer ihren Kranführer so unter Druck, dass beinahe ein Unglück passiert.",
		"ChannelName": "ProSieben MAXX",
		"Start": "2018-09-12T07:12:38+02:00",
		"Stop": "2018-09-12T08:03:43+02:00",
		"Info": {}
	},
	{
		"Title": "Gesetzeshüter der Wildnis",
		"Subtitle": "",
		"Summary": "",
		"Description": "Tief in den Wäldern von Maine lauern Gefahren hinter jedem Baumstamm. Gesetzeshüter Herring entdeckt heute einen illegalen Campingplatz auf Privatgelände. Stevens stößt hingegen auf eine illegale Marihuana-Plantage.",
		"ChannelName": "ProSieben MAXX",
		"Start": "2018-09-12T08:03:43+02:00",
		"Stop": "2018-09-12T08:51:59+02:00",
		"Info": {}
	},
	{
		"Title": "Gesetzeshüter der Wildnis",
		"Subtitle": "",
		"Summary": "",
		"Description": "Die Gesetzeshüter sorgen sowohl an Land als auch auf dem Wasser für Sicherheit. Heute schickt McBrine einen Helikopter an den Schauplatz eines schweren Unfalls und Buuck klärt über die Sicherheitsvorrichtungen auf Booten auf.",
		"ChannelName": "ProSieben MAXX",
		"Start": "2018-09-12T08:51:59+02:00",
		"Stop": "2018-09-12T09:40:24+02:00",
		"Info": {}
	},
	{
		"Title": "Border Patrol Australia",
		"Subtitle": "",
		"Summary": "",
		"Description": "Ein Mann erzählt den Beamten, dass er in Bali war, um entspannt Urlaub zu machen. Doch der Drogentest beweist etwas anderes. Auch eine Frau, die sich ihrer Schuhe entledigen will, gerät in den Fokus der Kontrolleure.",
		"ChannelName": "ProSieben MAXX",
		"Start": "2018-09-12T09:40:24+02:00",
		"Stop": "2018-09-12T10:07:01+02:00",
		"Info": {}
	},
	{
		"Title": "Border Patrol Australia",
		"Subtitle": "",
		"Summary": "",
		"Description": "Die Beamten vermuten eine Verbindung zwischen zwei Männern, die beide nach Australien einreisen wollen und über ihre Einreisegründe nur vage Angaben machen. Außerdem täuscht ein Engländer einen Amnesie-Anfall vor.",
		"ChannelName": "ProSieben MAXX",
		"Start": "2018-09-12T10:07:01+02:00",
		"Stop": "2018-09-12T10:34:00+02:00",
		"Info": {}
	},
	{
		"Title": "Border Patrol Australia",
		"Subtitle": "",
		"Summary": "",
		"Description": "Als die Beamten im Gepäck eines Mannes große Mengen an weißem Puder finden, wird dieser zornig. Außerdem landet ein Neuseeländer mit dem Ziel, endlich ein neues Leben zu beginnen. Doch wie sich bald herausstellt, hat er eine kriminelle Vergangenheit. Und eine Familie versucht, eine exotische Box mit merkwürdigen Inhalten einzuführen",
		"ChannelName": "ProSieben MAXX",
		"Start": "2018-09-12T10:34:00+02:00",
		"Stop": "2018-09-12T11:01:11+02:00",
		"Info": {}
	},
	{
		"Title": "Border Patrol Australia",
		"Subtitle": "",
		"Summary": "",
		"Description": "Als die Aussagen zweier Frauen nicht zu stimmen scheinen, sind sich die Beamten sicher, dass diese etwas verstecken. Außerdem gibt ein Mann an, um die halbe Welt gereist zu sein, um drei kleine Taschen mit einer seltsamen Substanz abzuholen.",
		"ChannelName": "ProSieben MAXX",
		"Start": "2018-09-12T11:01:11+02:00",
		"Stop": "2018-09-12T11:29:16+02:00",
		"Info": {}
	},
	{
		"Title": "Gesetzeshüter der Wildnis",
		"Subtitle": "",
		"Summary": "",
		"Description": "Wenn die wilden Tiere aus den Wäldern Maines in das Territorium der Menschen vordringen, ist die Hilfe der Gesetzeshüter der Wildnis gefragt. Heute sind Marquis und Fitzpatrick einem Bären auf der Spur, der gerne Müllcontainer durchforstet.",
		"ChannelName": "ProSieben MAXX",
		"Start": "2018-09-12T11:29:16+02:00",
		"Stop": "2018-09-12T12:19:01+02:00",
		"Info": {}
	},
	{
		"Title": "Gesetzeshüter der Wildnis",
		"Subtitle": "",
		"Summary": "",
		"Description": "Gesetzeshüter Judd kümmert sich heute um ein Stinktier-Junges, das sich in einem sehr schlechten Zustand befindet. Unterdessen suchen MacCabe und Robertson in den Wäldern nach einem verschwundenen Quad.",
		"ChannelName": "ProSieben MAXX",
		"Start": "2018-09-12T12:19:01+02:00",
		"Stop": "2018-09-12T13:08:36+02:00",
		"Info": {}
	},
	{
		"Title": "Border Patrol Australia",
		"Subtitle": "",
		"Summary": "",
		"Description": "Religiöse Statuen kommen den Beamten verdächtig vor und werden daher näher untersucht. Außerdem gerät ein Passagier in eine ernste Lage, als die Beamten entdecken, dass er mit hochexplosivem Material geflogen ist ...",
		"ChannelName": "ProSieben MAXX",
		"Start": "2018-09-12T13:08:36+02:00",
		"Stop": "2018-09-12T13:35:54+02:00",
		"Info": {}
	},
	{
		"Title": "Border Patrol Australia",
		"Subtitle": "",
		"Summary": "",
		"Description": "Als ein Drogenspürhund bei einem Mann anschlägt, halten die Beamten diesen sofort auf. Außerdem wird ein Officer bei der Farbe eines Getränkepulvers skeptisch.",
		"ChannelName": "ProSieben MAXX",
		"Start": "2018-09-12T13:35:54+02:00",
		"Stop": "2018-09-12T14:03:44+02:00",
		"Info": {}
	},
	{
		"Title": "Border Patrol Australia",
		"Subtitle": "",
		"Summary": "",
		"Description": "Heute entdecken die Beamten in der Hose eines Mannes eine Überraschung. Außerdem wird ein Staubsauger genauer unter die Lupe genommen, und die geplante Tour einer Rock-Band droht zu platzen.",
		"ChannelName": "ProSieben MAXX",
		"Start": "2018-09-12T14:03:44+02:00",
		"Stop": "2018-09-12T14:31:32+02:00",
		"Info": {}
	},
	{
		"Title": "Border Patrol Australia",
		"Subtitle": "",
		"Summary": "",
		"Description": "Heute haben es die Beamten mit einer Boxerin zu tun, die zwei verschiedene Identitäten hat. Außerdem will ein jungvermähltes Paar mit ungewöhnlichen Hochzeitsgeschenken einreisen.",
		"ChannelName": "ProSieben MAXX",
		"Start": "2018-09-12T14:31:32+02:00",
		"Stop": "2018-09-12T14:59:01+02:00",
		"Info": {}
	},
	{
		"Title": "Futurama",
		"Subtitle": "",
		"Summary": "",
		"Description": "Hermes verfolgt das Ziel, den nutzlosesten \"Planet Express\"-Angestellten am Ende des Tages zu feuern. Leider stellt sich heraus, dass er selbst den sinnlosesten Job hat. Kurzerhand entlässt er sich selbst und wird durch eine Bürokratenmaschine ersetzt. Das kann Hermes jedoch nicht auf sich sitzen lassen und beschließt, sich \"upzugraden\". Er baut nach und nach maschinelle Teile in seinen Körper ein, um es an Effizienz mit seinem maschinellen Konkurrenten aufnehmen zu können.\n\nRegie: Peter Avanzino\nDrehbuch: Ken Keeler\nKomponist: Christopher Tyng\nSchnitt: Paul D. Calder",
		"ChannelName": "ProSieben MAXX",
		"Start": "2018-09-12T14:59:01+02:00",
		"Stop": "2018-09-12T15:24:53+02:00",
		"Info": {
			"Drehbuch": [
				"Ken Keeler"
			],
			"Komponist": [
				"Christopher Tyng"
			],
			"Regie": [
				"Peter Avanzino"
			]
		}
	},
	{
		"Title": "Family Guy",
		"Subtitle": "",
		"Summary": "",
		"Description": "Brian befolgt den Rat seines Therapeuten, anderen zu helfen, und verpflichtet sich als Drogenschnüffelhund. Er erweist sich als sehr erfolgreich - mit dem Nebeneffekt, dass er selbst kokainsüchtig wird. Die Griffins müssen nun leider ihren Urlaub auf den Bahamas absagen, um Brian bei seiner Entziehungskur zu helfen. Als ihm erklärt wird, dass Peter kein guter Umgang für ihn ist, verlässt Brian verärgert die Klinik ...\n\nRegie: Glen Hill\nDrehbuch: Steve Callaghan",
		"ChannelName": "ProSieben MAXX",
		"Start": "2018-09-12T15:24:53+02:00",
		"Stop": "2018-09-12T15:51:11+02:00",
		"Info": {
			"Regie": [
				"Glen Hill"
			]
		}
	},
	{
		"Title": "Yu-Gi-Oh! 5D's",
		"Subtitle": "",
		"Summary": "",
		"Description": "Yusei und seine Freunde verhören Lazar. Doch statt wie von Lazar angekündigt über die Yliaster zu berichten, weicht er aus und erzählt über seine eigene Vergangenheit ...",
		"ChannelName": "ProSieben MAXX",
		"Start": "2018-09-12T15:51:11+02:00",
		"Stop": "2018-09-12T16:17:43+02:00",
		"Info": {}
	},
	{
		"Title": "Dragon Ball Z Kai",
		"Subtitle": "",
		"Summary": "",
		"Description": "Vegeta kann die Menschen auf der Erde nicht dazu bewegen, Son Goku ihre Kraft zukommen zu lassen. Doch dann nimmt sich einmal mehr Mister Satan der Sachen an, damit die Genkidama gelingt und Boo endlich ausgelöscht wird.",
		"ChannelName": "ProSieben MAXX",
		"Start": "2018-09-12T16:17:43+02:00",
		"Stop": "2018-09-12T16:44:02+02:00",
		"Info": {}
	},
	{
		"Title": "Hunter x Hunter",
		"Subtitle": "",
		"Summary": "",
		"Description": "Gon und Co. müssen ihre verwettete Zeit absitzen, und auch danach stellen sich ihnen neue Probleme in den Weg.",
		"ChannelName": "ProSieben MAXX",
		"Start": "2018-09-12T16:44:02+02:00",
		"Stop": "2018-09-12T17:11:33+02:00",
		"Info": {}
	},
	{
		"Title": "Eureka Seven",
		"Subtitle": "",
		"Summary": "",
		"Description": "Charles und Ray wollen die gesamte Crew sowie die Gekko eliminieren. Indessen haben Renton und Holland so einiges zu klären.",
		"ChannelName": "ProSieben MAXX",
		"Start": "2018-09-12T17:11:33+02:00",
		"Stop": "2018-09-12T17:39:19+02:00",
		"Info": {}
	},
	{
		"Title": "Naruto Shippuden",
		"Subtitle": "",
		"Summary": "",
		"Description": "Während sich Naruto und Sai im Krankenhaus von den Folgen der vergangenen Krise langsam erholen, muss Tsunade wegen ihres Verhaltens jede Menge Kritik einstecken. Hinzu kommt, dass die nächsten schlechten Nachrichten nicht lange auf sich warten lassen ...",
		"ChannelName": "ProSieben MAXX",
		"Start": "2018-09-12T17:39:19+02:00",
		"Stop": "2018-09-12T18:02:58+02:00",
		"Info": {}
	},
	{
		"Title": "Naruto Shippuden",
		"Subtitle": "",
		"Summary": "",
		"Description": "Naruto ist kaum noch vom Training wegzubekommen, weil er endlich die Chakra-Manipulation einsetzen können will. Es sieht so aus, als sollte er diese Fähigkeit schon bald benötigen, denn Kakuzu und Hidan brechen in den Feuer-Tempel ein. Wieder steckt Akatsuki hinter der Aktion ...",
		"ChannelName": "ProSieben MAXX",
		"Start": "2018-09-12T18:02:58+02:00",
		"Stop": "2018-09-12T18:26:16+02:00",
		"Info": {}
	},
	{
		"Title": "Gintama",
		"Subtitle": "",
		"Summary": "",
		"Description": "Kagura gewinnt eine Reise in den Weltraum. Doch auf dem Weg dorthin, wird das Raumschiff entführt ...",
		"ChannelName": "ProSieben MAXX",
		"Start": "2018-09-12T18:26:16+02:00",
		"Stop": "2018-09-12T18:54:08+02:00",
		"Info": {}
	},
	{
		"Title": "One Piece",
		"Subtitle": "",
		"Summary": "",
		"Description": "Während Sharley eine Vision hat, die die angebliche Zukunft der gesamten Insel vorhersagt, wird ebenfalls deutlich, warum König Neptun vor Jahren mit seinem Sohn eine Armee gegründet hat und wer in der Vergangenheit eigentlich für den Schutz der Insel zuständig war ...",
		"ChannelName": "ProSieben MAXX",
		"Start": "2018-09-12T18:54:08+02:00",
		"Stop": "2018-09-12T19:19:07+02:00",
		"Info": {}
	},
	{
		"Title": "Futurama",
		"Subtitle": "",
		"Summary": "",
		"Description": "Professor Farnsworth lädt die Crew auf das Oktoberfest ein. Fry freut sich wie verrückt, muss aber enttäuscht feststellen, dass das Oktoberfest in der Zukunft nichts mehr mit dem ursprünglichen bayrischen Saufgelage zu tun hat, das er so liebt. Bender will an einem Wurstmacher-Wettbewerb teilnehmen und braucht dazu ganz besonderes Fleisch. Er fliegt mit Fry ins Neandertal, um dort aus dem ewigen Eis ein tiefgefrorenes Mammut zu holen ...\n\nRegie: Stephen Sandoval\nDrehbuch: Dan Vebber\nKomponist: Christopher Tyng\nSchnitt: Paul D. Calder",
		"ChannelName": "ProSieben MAXX",
		"Start": "2018-09-12T19:19:07+02:00",
		"Stop": "2018-09-12T19:46:49+02:00",
		"Info": {
			"Drehbuch": [
				"Dan Vebber"
			],
			"Komponist": [
				"Christopher Tyng"
			],
			"Regie": [
				"Stephen Sandoval"
			]
		}
	},
	{
		"Title": "Family Guy",
		"Subtitle": "",
		"Summary": "",
		"Description": "Brian will seinem Leben eine neue Wendung geben und zieht nach Hollywood, wo er zunächst als Reinigungskraft arbeitet. Schließlich gelingt es ihm, sein Drehbuch einem Produzenten vorzulegen, und der bietet ihm gleich eine Stelle als Regisseur an - für Pornofilme. Der Erfolg lässt nicht lange auf sich warten: Brian erhält einen Filmpreis, den Woody ... Stewie hat indes einen Auftritt in einer Unterhaltungs-Show gewonnen. Die Griffins machen sich auf den Weg nach L.A. ...\n\nRegie: Gavin Dell\nDrehbuch: Gary Janetti\nKomponist: Ron Jones",
		"ChannelName": "ProSieben MAXX",
		"Start": "2018-09-12T19:46:49+02:00",
		"Stop": "2018-09-12T20:14:22+02:00",
		"Info": {
			"Drehbuch": [
				"Gary Janetti"
			],
			"Regie": [
				"Gavin Dell"
			]
		}
	},
	{
		"Title": "Two and a Half Men",
		"Subtitle": "",
		"Summary": "",
		"Description": "Larry ahnt immer noch nicht, dass Lyndsey und Alan hinter seinem Rücken eine Affäre haben. Als Larry Alan zu einem Doppel-Date mit seiner attraktiven Kollegin Gwen und Lindsey einlädt, willigt er ein. Das Date nimmt jedoch eine verhängnisvolle Wendung. Walden hat sich Hals über Kopf in Nicole verknallt, die eine Software zur Gedankenerkennung entwickelt und aus diesem Grund kaum Zeit für ihn hat. Schließlich nimmt sie seine Hilfe an. Leider hat ihr Kompagnon Barry etwas dagegen.\n\nGaststar: Jeff Probst\nRegie: James Widdoes\nDrehbuch: Don Reo, Susan McMartin, Leslie Schapira\nAutor: Lee Aronsohn, Chuck Lorre\nKomponist: Dennis C. Brown, Grant Geissman\n\nDarsteller:\nJon Cryer (Alan Harper)\nAshton Kutcher (Walden Schmidt)\nD.B. Sweeney (Larry)\nCourtney Thorne-Smith (Lyndsey)\nBrooke Lyons (Gwen)\nOdette Annable (Nicole)\nClark Duke (Barry)",
		"ChannelName": "ProSieben MAXX",
		"Start": "2018-09-12T20:14:22+02:00",
		"Stop": "2018-09-12T20:42:52+02:00",
		"Info": {
			"Autor": [
				"Lee Aronsohn",
				"Chuck Lorre"
			],
			"Drehbuch": [
				"Don Reo",
				"Susan McMartin",
				"Leslie Schapira"
			],
			"Gaststar": [
				"Jeff Probst"
			],
			"Komponist": [
				"Dennis C. Brown",
				"Grant Geissman"
			],
			"Regie": [
				"James Widdoes"
			]
		}
	},
	{
		"Title": "Two and a Half Men",
		"Subtitle": "",
		"Summary": "",
		"Description": "Evelyns Freund Marty macht ihr einen Heiratsantrag und bittet Walden, Trauzeuge zu werden. Vor der Hochzeit veranstaltet Walden für den Senior einen Junggesellenabschied. Der Höhepunkt des Abends - der Auftritt zweier Stripperinnen - bringt Marty zunächst von seinen Hochzeitsplänen ab. Mit vollem Einsatz schaffen es Alan und Walden, ihn umzustimmen. Der alte Mann, der die beiden für ein schwules Pärchen hält, revanchiert sich mit einer ganz besonderen Überraschung ...\n\nRegie: James Widdoes\nDrehbuch: Tim Kelleher, Jeff Lowell, James Vallely\nAutor: Lee Aronsohn, Chuck Lorre\nKomponist: Dennis C. Brown, Grant Geissman\nKamera: Mark Davison\nSchnitt: Joe Bella\n\nDarsteller:\nJon Cryer (Alan Harper)\nAshton Kutcher (Walden Schmidt)\nConchata Ferrell (Berta)\nCarl Reiner (Marty Pepper)\nAmber Tamblyn (Jenny)\nHolland Taylor (Evelyn)\nMaria Zyrianova (Sugar)\nAndrea Carlisle (Cinnamon)\nTim Conway (Tim)",
		"ChannelName": "ProSieben MAXX",
		"Start": "2018-09-12T20:42:52+02:00",
		"Stop": "2018-09-12T21:12:05+02:00",
		"Info": {
			"Autor": [
				"Lee Aronsohn",
				"Chuck Lorre"
			],
			"Drehbuch": [
				"Tim Kelleher",
				"Jeff Lowell",
				"James Vallely"
			],
			"Kamera": [
				"Mark Davison"
			],
			"Komponist": [
				"Dennis C. Brown",
				"Grant Geissman"
			],
			"Regie": [
				"James Widdoes"
			],
			"Schnitt": [
				"Joe Bella"
			]
		}
	},
	{
		"Title": "Two and a Half Men",
		"Subtitle": "",
		"Summary": "",
		"Description": "Walden muss bei seinem Auto einen Reifen wechseln, was ihn vor echte Probleme stellt. Für Brooke ist die Sache klar: Er ist eben kein echter Kerl. Das kann Walden nicht auf sich sitzen lassen. Um seine Männlichkeit zu beweisen, stürzt er sich in Handwerkertätigkeiten. Unter anderem baut er die Terrasse des Hauses neu auf. Leider überschätzt Walden sein handwerkliches Geschick etwas ...\n\nRegie: James Widdoes\nDrehbuch: Maria Espada Pearce, Don Reo, Jim Patterson\nAutor: Lee Aronsohn, Chuck Lorre\nKomponist: Dennis C. Brown, Grant Geissman\nKamera: Bruce Davison\nSchnitt: Joe Bella\n\nDarsteller:\nJon Cryer (Alan Harper)\nAshton Kutcher (Walden Schmidt)\nConchata Ferrell (Berta)\nAmber Tamblyn (Jenny)\nElle Evans (Cheyenne)\nAly Michalka (Brooke)\nD.B. Sweeney (Larry)\nCourtney Thorne-Smith (Lyndsey)",
		"ChannelName": "ProSieben MAXX",
		"Start": "2018-09-12T21:12:05+02:00",
		"Stop": "2018-09-12T21:33:52+02:00",
		"Info": {
			"Autor": [
				"Lee Aronsohn",
				"Chuck Lorre"
			],
			"Drehbuch": [
				"Maria Espada Pearce",
				"Don Reo",
				"Jim Patterson"
			],
			"Kamera": [
				"Bruce Davison"
			],
			"Komponist": [
				"Dennis C. Brown",
				"Grant Geissman"
			],
			"Regie": [
				"James Widdoes"
			],
			"Schnitt": [
				"Joe Bella"
			]
		}
	},
	{
		"Title": "The Last Man on Earth",
		"Subtitle": "",
		"Summary": "",
		"Description": "Gail steckt noch immer im Aufzug fest, und langsam macht sich bei ihr Verzweiflung breit. Doch dann hat sie einen Hoffnungsschimmer: Nach etlichen Versuchen gelingt es ihr, einen Zettel an einem vorbeifahrenden Staubsaugerroboter anzubringen. Melissas psychische Probleme scheinen sich derweil zu verschlimmern, denn als Todd auf der Suche nach ihr ist, findet er sie auf einem Dach - kurz davor, in den Tod zu stürzen. Todd sieht nur eine Möglichkeit, um Melissa zu beschützen ...\n\nRegie: Jason Woliner\nDrehbuch: Erik Durbin, Will Forte\nKomponist: John Enroth, Albert Fox, Mark Mothersbaugh\nKamera: Carl Herse\nSchnitt: Sam Seig\n\nDarsteller:\nWill Forte (Phil Miller / Tandy)\nKristen Schaal (Carol Pilbasian)\nJanuary Jones (Melissa Chartres)\nCleopatra Coleman (Erica)\nMel Rodriguez (Todd)",
		"ChannelName": "ProSieben MAXX",
		"Start": "2018-09-12T21:33:52+02:00",
		"Stop": "2018-09-12T22:01:29+02:00",
		"Info": {
			"Drehbuch": [
				"Erik Durbin",
				"Will Forte"
			],
			"Kamera": [
				"Carl Herse"
			],
			"Komponist": [
				"John Enroth",
				"Albert Fox",
				"Mark Mothersbaugh"
			],
			"Regie": [
				"Jason Woliner"
			],
			"Schnitt": [
				"Sam Seig"
			]
		}
	},
	{
		"Title": "RAW",
		"Subtitle": "",
		"Summary": "",
		"Description": "Moderation: Holger Böschen, Sebastian Hackl\n\nProSieben MAXX strahlt mittwochs um 22:00 Uhr die WWE Flaggschiff-Show \"RAW\" aus - exklusiv im Free-TV. Hier treten Roman Reigns, Seth Rollins und Brock Lesnar gegeneinander an, um WWE Universal Champion zu werden. Doch sie sind nicht die einzigen Talents, die sich bei \"RAW\" einen Titel umschnallen wollen. Die weiblichen WWE Superstars rund um Sasha Banks, Bayley und Alexa Bliss wollen sich als WWE RAW Womens Champion krönen.",
		"ChannelName": "ProSieben MAXX",
		"Start": "2018-09-12T22:01:29+02:00",
		"Stop": "2018-09-13T00:00:22+02:00",
		"Info": {
			"Moderation": [
				"Holger Böschen",
				"Sebastian Hackl"
			]
		}
	}
]