[
	{
		"Title": "Homicide Hunter - Dem Mörder auf der Spur",
		"Subtitle": "",
		"Summary": "",
		"Description": "Ein Lastwagen kracht mit vollem Tempo in ein Gebäude. Am Steuer sitzt die Leiche des 31-jährigen Michael Faast. Er starb jedoch nicht beim Aufprall, sondern an einer Kugel in die Schläfe. Der einzige Augenzeuge kann die Ereignisse nur schwer rekonstruieren. Joe Kenda recherchiert daher im Umfeld des Opfers und stößt auf eine pikante und gefährliche Geschichte.\n\nExperte: Joe Kenda\n\nDarsteller:\nCarl Marino (Lt. Joe Kenda)",
		"ChannelName": "sixx",
		"Start": "2018-09-12T00:05:54+02:00",
		"Stop": "2018-09-12T00:58:46+02:00",
		"Info": {
			"Experte": [
				"Joe Kenda"
			]
		}
	},
	{
		"Title": "Ungeklärt - Mord verjährt nicht",
		"Subtitle": "",
		"Summary": "",
		"Description": "Ein aufstrebender Fotograf aus der Schweiz wird in seinem neuen Zuhause in Los Angeles brutal ermordet. Der Tatort liefert ein Bild des Grauens. Blut tropft von der Decke die Wände entlang, und das Opfer liegt bäuchlings auf dem Boden. Die Ermittler tauchen in sein fragwürdiges Umfeld ein und vermuten, dass der Fotograf seinen Mörder kannte ...",
		"ChannelName": "sixx",
		"Start": "2018-09-12T00:58:46+02:00",
		"Stop": "2018-09-12T01:46:53+02:00",
		"Info": {}
	},
	{
		"Title": "Ungeklärt - Mord verjährt nicht",
		"Subtitle": "",
		"Summary": "",
		"Description": "Im August 1993 geschehen in Spring Hill, Florida, eine Reihe gewaltsamer Verbrechen an älteren Menschen. Die Polizei ermittelt fieberhaft und geht von einem pyromanen Serientäter aus. Das FBI kommt den Ermittlern zu Hilfe und obwohl es eine Reihe an Verdächtigen gibt, gelingt es den Beamten zunächst nicht, den Killer zu finden.",
		"ChannelName": "sixx",
		"Start": "2018-09-12T01:46:53+02:00",
		"Stop": "2018-09-12T02:34:59+02:00",
		"Info": {}
	},
	{
		"Title": "Homicide Hunter - Dem Mörder auf der Spur",
		"Subtitle": "",
		"Summary": "",
		"Description": "Auf dem Flur eines Hauses in einem ruhigen Vorort liegen die Leichen zweier Schwestern - sie wurden erschossen. Keiner ihrer Freunde oder Nachbarn kann sich vorstellen, wer den jungen Müttern schaden wollte. Ermittler Kenda stößt auf ein pikantes Geheimnis, das ihn zu einem Hauptverdächtigen führt. Doch der Fall nimmt eine überraschende Wendung ...\n\nExperte: Joe Kenda\n\nDarsteller:\nCarl Marino (Lt. Joe Kenda)",
		"ChannelName": "sixx",
		"Start": "2018-09-12T02:34:59+02:00",
		"Stop": "2018-09-12T03:20:26+02:00",
		"Info": {
			"Experte": [
				"Joe Kenda"
			]
		}
	},
	{
		"Title": "Homicide Hunter - Dem Mörder auf der Spur",
		"Subtitle": "",
		"Summary": "",
		"Description": "Ein Lastwagen kracht mit vollem Tempo in ein Gebäude. Am Steuer sitzt die Leiche des 31-jährigen Michael Faast. Er starb jedoch nicht beim Aufprall, sondern an einer Kugel in die Schläfe. Der einzige Augenzeuge kann die Ereignisse nur schwer rekonstruieren. Joe Kenda recherchiert daher im Umfeld des Opfers und stößt auf eine pikante und gefährliche Geschichte.\n\nExperte: Joe Kenda\n\nDarsteller:\nCarl Marino (Lt. Joe Kenda)",
		"ChannelName": "sixx",
		"Start": "2018-09-12T03:20:26+02:00",
		"Stop": "2018-09-12T04:03:58+02:00",
		"Info": {
			"Experte": [
				"Joe Kenda"
			]
		}
	},
	{
		"Title": "Stalked - Leben in Angst",
		"Subtitle": "",
		"Summary": "",
		"Description": "Marie DePalma ist eine unscheinbare Schülerin aus Detroit, die es nicht kennt, von Jungs umworben zu werden. Als sie der ältere Schüler Luis anspricht und mit ihr flirtet, fühlt sich Marie sehr geschmeichelt und sie lässt sich auf den Jungen ein. Was sie zu dem Zeitpunkt noch nicht weiß: Luis ist Mitglied einer Gang und schon bald schwebt nicht nur Marie, sondern auch ihre Familie in Lebensgefahr.",
		"ChannelName": "sixx",
		"Start": "2018-09-12T04:03:58+02:00",
		"Stop": "2018-09-12T04:27:13+02:00",
		"Info": {}
	},
	{
		"Title": "Cold Case - Kein Opfer ist je vergessen",
		"Subtitle": "",
		"Summary": "",
		"Description": "Die Mutter eines 1994 wegen Mordes an drei Jungen zu lebenslänglich Verurteilen sucht Rush auf. Ihr Sohn hat sich im Gefängnis umgebracht, und unter seinen Habseligkeiten fand sie einen Brief, in dem sich ein Außenstehender der Tat bezichtigt. Der wegen Mittäterschaft ebenfalls verurteilte Dylan beteuert im Verhör ebenfalls seine Unschuld. Rush und ihre Kollegen ahnen bald, dass während der Ermittlungen Spuren nicht verfolgt und Beweise unterdrückt worden sind ...\n\nRegie: Alex Zakrzewski\nDrehbuch: Veena Cabreros Sud\nKomponist: Michael A. Levine\nKamera: Donald E. Thorin\nSchnitt: Maja Vrvilo\n\nDarsteller:\nKathryn Morris (Det. Lilly Rush)\nDanny Pino (Det. Scott Valens)\nJohn Finn (Lt. John Stillman)\nJeremy Ratchford (Det. Nick Vera)\nThom Barry (Det. Will Jeffries)\nTracie Thoms (Kat Miller)\nKirk Acevedo (Dylan Noakes)\nAndrew James Allen (Teddy Nimmo (1994))\nZylan Brooks (Jade Diaz)",
		"ChannelName": "sixx",
		"Start": "2018-09-12T04:27:13+02:00",
		"Stop": "2018-09-12T05:08:54+02:00",
		"Info": {
			"Drehbuch": [
				"Veena Cabreros Sud"
			],
			"Kamera": [
				"Donald E. Thorin"
			],
			"Komponist": [
				"Michael A. Levine"
			],
			"Regie": [
				"Alex Zakrzewski"
			],
			"Schnitt": [
				"Maja Vrvilo"
			]
		}
	},
	{
		"Title": "Watch Me - das Kinomagazin",
		"Subtitle": "",
		"Summary": "",
		"Description": "Aktuelle Kinofilme knackig und kompakt präsentiert - das bietet \"Watch Me - Das Kinomagazin\".",
		"ChannelName": "sixx",
		"Start": "2018-09-12T05:08:54+02:00",
		"Stop": "2018-09-12T05:18:52+02:00",
		"Info": {}
	},
	{
		"Title": "sixx QUICKIE",
		"Subtitle": "",
		"Summary": "",
		"Description": "Schnell. Informativ. Unterhaltsam. sixx QUICKIE informiert dich täglich über Aktuelles, Wissenswertes und Skurriles aus den Bereichen Fashion, Beauty, Lifestyle, Stars, Food, Reise, Dating und Sex.",
		"ChannelName": "sixx",
		"Start": "2018-09-12T05:18:52+02:00",
		"Stop": "2018-09-12T05:28:42+02:00",
		"Info": {}
	},
	{
		"Title": "Grey's Anatomy - Die jungen Ärzte",
		"Subtitle": "",
		"Summary": "",
		"Description": "Derek und Finn haben sich auf das Spiel eingelassen, um Meredith zu werben. Während es Finn zunächst mit einem Lunch in der Cafeteria versucht, den Derek abkürzt, indem er Meredith anbietet, bei einer Hirn-OP dabei zu sein, endet Dereks Dinner-Einladung damit, dass Finn am Ende vor Merediths Tür steht und ihr Erdbeer-Eis anbietet ... Indes kümmert sich Alex um die kleine Megan, die behauptet, sie wäre eine Superheldin. Es stellt sich heraus, dass sie keine Schmerzen empfindet ...\n\nRegie: Adam Arkin\nDrehbuch: Debora Cahn\nAutor: Shonda Rhimes\nKomponist: Danny Lux\nKamera: Herbert Davis\nSchnitt: Briana London, Edward Ornelas, Matthew Ramsey\n\nDarsteller:\nEllen Pompeo (Dr. Meredith Grey)\nJustin Chambers (Dr. Alex Karev)\nJames Pickens jr. (Dr. Richard Webber)\nChandra Wilson (Dr. Miranda Bailey)\nPatrick Dempsey (Dr. Derek Shepherd)\nSandra Oh (Dr. Cristina Yang)\nKatherine Heigl (Dr. Isobel \"Izzie\" Stevens)\nT. R. Knight (Dr. George O'Malley)\nIsaiah Washington (Dr. Preston Burke)",
		"ChannelName": "sixx",
		"Start": "2018-09-12T05:28:42+02:00",
		"Stop": "2018-09-12T06:10:29+02:00",
		"Info": {
			"Autor": [
				"Shonda Rhimes"
			],
			"Drehbuch": [
				"Debora Cahn"
			],
			"Kamera": [
				"Herbert Davis"
			],
			"Komponist": [
				"Danny Lux"
			],
			"Regie": [
				"Adam Arkin"
			],
			"Schnitt": [
				"Briana London",
				"Edward Ornelas",
				"Matthew Ramsey"
			]
		}
	},
	{
		"Title": "Desperate Housewives",
		"Subtitle": "",
		"Summary": "",
		"Description": "Das Pärchen Bob und Lee hat sich nichts dabei gedacht, als es einen Springbrunnen in seinen Garten gestellt hat. Doch da haben sie nicht mit ihren Nachbarn aus der Wisteria Lane gerechnet: Die stellen nämlich kurzerhand einen Nachbarschaftsverein auf die Beine, um über den Abriss des Brunnens zu sprechen. Als der Verein dann tatsächlich gegen den Brunnen stimmt, statten Bob und Lee der Vorsitzenden, Katherine, einen kurzen Besuch ab. Werden sie sie noch umstimmen können?\n\nRegie: David Grossman\nDrehbuch: Jason Ganzel\nAutor: Marc Cherry\nKomponist: Steve Jablonsky\nKamera: Lowell Peterson\nSchnitt: Greg Pastore\n\nDarsteller:\nTeri Hatcher (Susan)\nMarcia Cross (Bree)\nFelicity Huffman (Lynette)\nEva Longoria (Gabrielle)\nBrenda Strong (Mary Alice Young / Erzählerin)\nNicolette Sheridan (Edie Britt)\nDana Delany (Katherine Mayfair)\nTuc Watkins (Bob Hunter)\nKevin Rahm (Lee McDermott)",
		"ChannelName": "sixx",
		"Start": "2018-09-12T06:10:29+02:00",
		"Stop": "2018-09-12T07:03:55+02:00",
		"Info": {
			"Autor": [
				"Marc Cherry"
			],
			"Drehbuch": [
				"Jason Ganzel"
			],
			"Kamera": [
				"Lowell Peterson"
			],
			"Komponist": [
				"Steve Jablonsky"
			],
			"Regie": [
				"David Grossman"
			],
			"Schnitt": [
				"Greg Pastore"
			]
		}
	},
	{
		"Title": "Charmed - Zauberhafte Hexen",
		"Subtitle": "",
		"Summary": "",
		"Description": "Der teuflische Auftrag der Seherin ist tatsächlich erfüllt: Cole hat mit Phoebe ein Kind des Bösen gezeugt. Als das Ungeborene bereits im Mutterleib seine dämonischen Kräfte und auch seinen starken Hass auf Paige deutlich zum Ausdruck bringt, plant die Seherin Ungeheuerliches: Auf magische Weise will sie Phoebe das dämonische Kind aus deren Bauch stehlen und das Baby in ihren eigenen Leib verpflanzen. Sie hofft, so das Erbe um die Macht der Quelle antreten zu können.\n\nRegie: Mel Damski\nDrehbuch: Daniel Cerone\nKomponist: J. Peter Robinson, Jay Gruska\nKamera: Rick Gunter\nSchnitt: Derek Berlatsky\n\nDarsteller:\nAlyssa Milano (Phoebe Halliwell)\nHolly Marie Combs (Piper Halliwell)\nRose McGowan (Paige Matthews)\nDorian Gregory (Darryl Morris)\nBrian Krause (Leo Wyatt)\nJulian McMahon (Cole)\nDebbi Morgan (Seherin)\nJeff Meek (Dane)",
		"ChannelName": "sixx",
		"Start": "2018-09-12T07:03:55+02:00",
		"Stop": "2018-09-12T07:58:10+02:00",
		"Info": {
			"Drehbuch": [
				"Daniel Cerone"
			],
			"Kamera": [
				"Rick Gunter"
			],
			"Komponist": [
				"J. Peter Robinson",
				"Jay Gruska"
			],
			"Regie": [
				"Mel Damski"
			],
			"Schnitt": [
				"Derek Berlatsky"
			]
		}
	},
	{
		"Title": "Charmed - Zauberhafte Hexen",
		"Subtitle": "",
		"Summary": "",
		"Description": "Phoebe, Paige und Piper erhalten hohen Besuch: Der \"Engel der Vorsehung\" erscheint bei den drei zauberhaften Hexen und macht ihnen ein verführerisches Angebot. Wenn es den Schwestern gelänge, die Quelle alles Bösen zu zerstören, hätten sie die Gelegenheit, ihr Leben und ihre Bestimmung neu zu entwerfen. Sie könnten dann entweder ihre magischen Kräfte behalten oder ein ganz normales, dämonenfreies Leben führen. Wie werden sich die drei entscheiden?\n\nRegie: Brad Kern\nDrehbuch: Brad Kern\nKomponist: Jay Gruska\nKamera: Rick Gunter\nSchnitt: Derek Berlatsky\n\nDarsteller:\nAlyssa Milano (Phoebe Halliwell)\nHolly Marie Combs (Piper Halliwell)\nRose McGowan (Paige Matthews)\nDorian Gregory (Darryl Morris)\nBrian Krause (Leo Wyatt)\nJulian McMahon (Cole)\nDakin Matthews (Schicksalsengel)\nBruce Campbell (Jackman)\nSamantha Shelton (Selena)",
		"ChannelName": "sixx",
		"Start": "2018-09-12T07:58:10+02:00",
		"Stop": "2018-09-12T08:54:21+02:00",
		"Info": {
			"Drehbuch": [
				"Brad Kern"
			],
			"Kamera": [
				"Rick Gunter"
			],
			"Komponist": [
				"Jay Gruska"
			],
			"Regie": [
				"Brad Kern"
			],
			"Schnitt": [
				"Derek Berlatsky"
			]
		}
	},
	{
		"Title": "Charmed - Zauberhafte Hexen",
		"Subtitle": "",
		"Summary": "",
		"Description": "Meerjungfrau Mylie hat ein Abkommen mit einer Meerhexe: Sollte ihr Freund Craig ihr nicht innerhalb von dreißig Tagen eine Liebeserklärung machen, muss sie der Hexe ihre Unsterblichkeit überlassen. Als es immer unwahrscheinlicher wird, dass Craig noch rechtzeitig zu seinen Gefühlen steht, wendet sich Mylie Hilfe suchend an Phoebe. Diese hat allerdings gerade mit eigenen Problemen zu kämpfen: Als sie die Scheidung einreichen wollte, ist Cole plötzlich wieder aufgetaucht ...\n\nRegie: James L. Conway\nDrehbuch: Daniel Cerone\nKomponist: J. Peter Robinson\nKamera: Jonathan West\nSchnitt: Derek Berlatsky\n\nDarsteller:\nAlyssa Milano (Phoebe Halliwell)\nHolly Marie Combs (Piper Halliwell)\nRose McGowan (Paige)\nDorian Gregory (Darryl Morris)\nBrian Krause (Leo)\nJulian McMahon (Cole)\nJaime Pressly (Mylie)\nDan Gauthier (Craig)\nDiane Salinger (Meerhexe)",
		"ChannelName": "sixx",
		"Start": "2018-09-12T08:54:21+02:00",
		"Stop": "2018-09-12T09:51:08+02:00",
		"Info": {
			"Drehbuch": [
				"Daniel Cerone"
			],
			"Kamera": [
				"Jonathan West"
			],
			"Komponist": [
				"J. Peter Robinson"
			],
			"Regie": [
				"James L. Conway"
			],
			"Schnitt": [
				"Derek Berlatsky"
			]
		}
	},
	{
		"Title": "Charmed - Zauberhafte Hexen",
		"Subtitle": "",
		"Summary": "",
		"Description": "Die auf eigenen Wunsch zur Meerjungfrau mutierte Phoebe wird vom Dämon Necron angegriffen, der mit ihrer Hilfe Unsterblichkeit erlangen will. Während des Zweikampfes wird die ehemalige Hexe verletzt und kann gerade noch rechtzeitig mit Leos Hilfe entkommen. Während Phoebe nun zu Hause von ihren Schwestern festgehalten wird, hat der hartnäckige Dämon Necron genug Zeit, einen neuen Plan zu entwickeln. Er will Piper entführen, um Phoebe zu erpressen ...\n\nGaststar: Nancy O'Dell\nRegie: Mel Damski\nDrehbuch: Alison Schapker, Monica Breen\nKomponist: J. Peter Robinson\nKamera: Jonathan West\nSchnitt: Derek Berlatsky\n\nDarsteller:\nAlyssa Milano (Phoebe Halliwell)\nHolly Marie Combs (Piper Halliwell)\nRose McGowan (Paige)\nDorian Gregory (Darryl Morris)\nBrian Krause (Leo)\nJulian McMahon (Cole)\nFinola Hughes (Patty Halliwell)\nJudson Scott (Necron)\nDavid Reivers (Bob Cowan)",
		"ChannelName": "sixx",
		"Start": "2018-09-12T09:51:08+02:00",
		"Stop": "2018-09-12T10:47:13+02:00",
		"Info": {
			"Drehbuch": [
				"Alison Schapker",
				"Monica Breen"
			],
			"Gaststar": [
				"Nancy O'Dell"
			],
			"Kamera": [
				"Jonathan West"
			],
			"Komponist": [
				"J. Peter Robinson"
			],
			"Regie": [
				"Mel Damski"
			],
			"Schnitt": [
				"Derek Berlatsky"
			]
		}
	},
	{
		"Title": "Mein perfektes Hochzeitskleid! - Atlanta",
		"Subtitle": "",
		"Summary": "",
		"Description": "Nach einer lebensbedrohlichen Nieren-Erkrankung hat Braut Alyssa wieder neuen Lebensmut und freut sich auf die Auswahl ihres perfekten Hochzeitskleides. Braut Shornell steckt hingegen in einem Kleid-Dilemma und die Berater versuchen, sie daraus zu befreien.",
		"ChannelName": "sixx",
		"Start": "2018-09-12T10:47:13+02:00",
		"Stop": "2018-09-12T11:43:24+02:00",
		"Info": {}
	},
	{
		"Title": "My Fair Wedding - In drei Wochen zur Traumhochzeit",
		"Subtitle": "",
		"Summary": "",
		"Description": "Braut Varneka lebt in einer beschaulichen Stadt in Delaware, will aber für ihre Hochzeitsfeier den Geist New Yorks in ihre Location bringen. Außerdem hat Varneka ein Faible für die Farbe Gold. David Tutera hält sie davon ab, jedes Deko-Element in ihrer Lieblingsfarbe zu kaufen und sorgt für die ein oder andere New York-taugliche Überraschung.\n\nExperte: David Tutera",
		"ChannelName": "sixx",
		"Start": "2018-09-12T11:43:24+02:00",
		"Stop": "2018-09-12T12:41:02+02:00",
		"Info": {}
	},
	{
		"Title": "Der Hundeflüsterer",
		"Subtitle": "",
		"Summary": "",
		"Description": "Angel und Bear sind die beiden deutschen Schäferhunde von Familie Carrick. Zu Beginn waren sie unzertrennlich, doch nun gehen sie ständig aufeinander los und beißen sich bis aufs Blut. Cesar gibt sein Bestes, um die Harmonie wiederherzustellen. Außerdem kümmert er sich um den kleinen Schnauzer Lorelei, der nichts als Ärger macht und Besucher wie verrückt anbellt.\n\nCoach: Cesar Millan",
		"ChannelName": "sixx",
		"Start": "2018-09-12T12:41:02+02:00",
		"Stop": "2018-09-12T13:40:07+02:00",
		"Info": {}
	},
	{
		"Title": "Der Hundeflüsterer",
		"Subtitle": "",
		"Summary": "",
		"Description": "Pauline Mercado und ihre Tochter Christine sind stolze Besitzerinnen zweier Chihuahuas, die sich auch noch prächtig verstehen. Doch seit Christine wegen des Studiums von zuhause ausgezogen ist, bekämpfen sich Peanut und Chico plötzlich. Auch Hund Leroy Brown macht Probleme: Jedesmal, wenn sein Herrchen aus der Tür will, springt er ihn an und bellt wie verrückt. Schließlich kümmert sich Cesar auch um den jungen Rüden Tucker, der von Wasser besessen ist.\n\nCoach: Cesar Millan",
		"ChannelName": "sixx",
		"Start": "2018-09-12T13:40:07+02:00",
		"Stop": "2018-09-12T14:32:57+02:00",
		"Info": {}
	},
	{
		"Title": "Der Hundeflüsterer",
		"Subtitle": "",
		"Summary": "",
		"Description": "Jeder Hund kann aggressive Verhaltensweisen an den Tag legen, doch es gibt Rassen, die von der Gesellschaft als besonders gefährlich eingestuft werden. Dies beweist auch eine Studie, die von der Redaktion des \"Hundeflüsterers\" in Auftrag gegeben wurde. Cesar Millan besucht heute die aggressivsten Hunde, die er in seiner Laufbahn kennengelernt hat. Kann er die Ergebnisse der Studie doch widerlegen?\n\nCoach: Cesar Millan",
		"ChannelName": "sixx",
		"Start": "2018-09-12T14:32:57+02:00",
		"Stop": "2018-09-12T15:31:17+02:00",
		"Info": {}
	},
	{
		"Title": "Sex and the City",
		"Subtitle": "",
		"Summary": "",
		"Description": "Carrie lässt sich auf eine Affäre mit Aleksandr Petrovsky ein. Sie genießt die Aufmerksamkeit, mit der ihr Lover sie überhäuft - wenngleich sie sich die Frage stellt, ob sie die Einzige ist, die in diesen Genuss kommt ... Samantha befürchtet indessen, dass ihre Beziehung zu Smith zu intensiv wird. Um sich zu beweisen, dass er eigentlich nicht das ist, was sie braucht, greift sie spontan zu, als sich die Gelegenheit zu einem kleinen Seitensprung mit ihrem Ex Richard ergibt ...\n\nRegie: Michael Patrick King\nDrehbuch: Michael Patrick King\nAutor: Candace Bushnell\nKomponist: Douglas J. Cuomo\nKamera: Florian Ballhaus\n\nDarsteller:\nSarah Jessica Parker (Carrie Bradshaw)\nKim Cattrall (Samantha Jones)\nKristin Davis (Charlotte York)\nCynthia Nixon (Miranda Hobbes)\nMikhail Baryshnikov (Aleksandr Petrovsky)\nBlair Underwood (Dr. Robert Leeds)\nDavid Eigenberg (Steve Brady)\nJason Lewis (Smith Jerrod)",
		"ChannelName": "sixx",
		"Start": "2018-09-12T15:31:17+02:00",
		"Stop": "2018-09-12T16:06:55+02:00",
		"Info": {
			"Autor": [
				"Candace Bushnell"
			],
			"Drehbuch": [
				"Michael Patrick King"
			],
			"Kamera": [
				"Florian Ballhaus"
			],
			"Komponist": [
				"Douglas J. Cuomo"
			],
			"Regie": [
				"Michael Patrick King"
			]
		}
	},
	{
		"Title": "Sex and the City",
		"Subtitle": "",
		"Summary": "",
		"Description": "Aleksandr Petrovsky ist ein Romantiker der alten Schule, der Carrie jeden Wunsch von den Augen abliest, ihr Gedichte vorliest und Klaviermusik für sie schreibt. Carrie hat jedoch bald das Gefühl, einer Überdosis Romantik zu erliegen ... Miranda und Steve heiraten. Auf der Feier nach der Trauung überrascht Samantha ihre Freundinnen mit einer Neuigkeit: Bei einer Brustuntersuchung hat der Arzt einen Knoten in ihrer linken Brust festgestellt - sie hat Krebs ...\n\nRegie: Wendy Stanzler\nDrehbuch: Julie Rottenberg, Elisa Zuritsky\nAutor: Candace Bushnell\nKomponist: Douglas J. Cuomo, Bob Christianson, Didier Rachou\nKamera: Florian Ballhaus\nSchnitt: Michael Berenbaum\n\nDarsteller:\nSarah Jessica Parker (Carrie Bradshaw)\nKim Cattrall (Samantha Jones)\nKristin Davis (Charlotte York)\nCynthia Nixon (Miranda Hobbes)\nMikhail Baryshnikov (Aleksandr Petrovsky)\nEvan Handler (Harry Goldenblatt)\nDavid Eigenberg (Steve Brady)",
		"ChannelName": "sixx",
		"Start": "2018-09-12T16:06:55+02:00",
		"Stop": "2018-09-12T16:39:26+02:00",
		"Info": {
			"Autor": [
				"Candace Bushnell"
			],
			"Drehbuch": [
				"Julie Rottenberg",
				"Elisa Zuritsky"
			],
			"Kamera": [
				"Florian Ballhaus"
			],
			"Komponist": [
				"Douglas J. Cuomo",
				"Bob Christianson",
				"Didier Rachou"
			],
			"Regie": [
				"Wendy Stanzler"
			],
			"Schnitt": [
				"Michael Berenbaum"
			]
		}
	},
	{
		"Title": "Desperate Housewives",
		"Subtitle": "",
		"Summary": "",
		"Description": "Danielle langweilt sich, weil sie nicht das Haus verlassen darf. Als sie aber von der Halloween-Party ihrer Nachbarn hört, scheint sie einen Weg gefunden zu haben, um trotz des Verbotes ihrer Mutter ausgehen zu können. Sie verkleidet sich als ihre Mutter und erscheint so auf der Party. Doch plötzlich platzt ihre Fruchtblase und Danielle überkommt die Angst, dass jemand von ihrem Geheimnis erfahren könnte. Als Adam schließlich zur Geburt geholt wird, verspricht er zu schweigen.\n\nRegie: Larry Shaw\nDrehbuch: Susan Nirah Jaffe, Dahvi Waller\nAutor: Marc Cherry\nKomponist: Steve Jablonsky\nKamera: Eric Van Haren Noman\nSchnitt: Michael Berenbaum, Kaja Fehr, Brent White\n\nDarsteller:\nTeri Hatcher (Susan)\nMarcia Cross (Bree)\nFelicity Huffman (Lynette)\nEva Longoria (Gabrielle)\nBrenda Strong (Mary Alice Young / Erzählerin)\nNicolette Sheridan (Edie Britt)\nJoy Lauren (Danielle Van De Kamp)\nNathan Fillion (Adam Mayfair)\nJames Denton (Mike Delfino)",
		"ChannelName": "sixx",
		"Start": "2018-09-12T16:39:26+02:00",
		"Stop": "2018-09-12T17:34:40+02:00",
		"Info": {
			"Autor": [
				"Marc Cherry"
			],
			"Drehbuch": [
				"Susan Nirah Jaffe",
				"Dahvi Waller"
			],
			"Kamera": [
				"Eric Van Haren Noman"
			],
			"Komponist": [
				"Steve Jablonsky"
			],
			"Regie": [
				"Larry Shaw"
			],
			"Schnitt": [
				"Michael Berenbaum",
				"Kaja Fehr",
				"Brent White"
			]
		}
	},
	{
		"Title": "Cold Case - Kein Opfer ist je vergessen",
		"Subtitle": "",
		"Summary": "",
		"Description": "Diesmal beschäftigt die Ermittler der bisher älteste ungelöste Mordfall Philadelphias. Frances Stone, Tochter eines vermögenden Brauereibesitzers, starb 1919 durch einen Sturz im Treppenhaus. Sie war mit einem Mann aus den besten Kreisen verlobt und hatte Beziehungen zur Bewegung der Frauenrechtlerinnen. Die Nachforschungen führen zu den Anfängen der Frauenrebellion und in eine Zeit, in der der Widerstand gegen diese Emanzipation auch aus den Reihen der Frauen selbst kam ...\n\nRegie: Kevin Bray\nDrehbuch: Tyler Bensinger\nKomponist: Michael A. Levine\nKamera: Donald E. Thorin jr.\n\nDarsteller:\nKathryn Morris (Det. Lilly Rush)\nDanny Pino (Det. Scott Valens)\nJohn Finn (Lt. John Stillman)\nJeremy Ratchford (Det. Nick Vera)\nThom Barry (Det. Will Jeffries)\nErin Cahill (Francis Stone)\nZach Grenier (Ambrose Stone)\nJudson Morgan (Lawrence Wakeley)\nTracie Thoms (Kat Miller)",
		"ChannelName": "sixx",
		"Start": "2018-09-12T17:34:40+02:00",
		"Stop": "2018-09-12T18:28:49+02:00",
		"Info": {
			"Drehbuch": [
				"Tyler Bensinger"
			],
			"Kamera": [
				"Donald E. Thorin jr."
			],
			"Komponist": [
				"Michael A. Levine"
			],
			"Regie": [
				"Kevin Bray"
			]
		}
	},
	{
		"Title": "Unforgettable",
		"Subtitle": "",
		"Summary": "",
		"Description": "Ein reiches Ehepaar wird in seiner Wohnung ermordet, die Eheringe sind verschwunden. Vor drei Jahren hat Al bereits in zwei Doppelmorden mit dem gleichen Tathergang ermittelt. Wie Carrie und ihr Team herausfinden, kannten sich die drei Paare. Die drei Ehemänner waren zudem Kunden beim Escort-Service von Eileen Brenner. Carrie und Al geben sich als Ehepaar aus, und Al trifft sich mit einer der jungen Escort-Damen, um den Täter in eine Falle zu locken.\n\nRegie: Jan Eliasberg\nDrehbuch: Barry Schindel\n\nDarsteller:\nPoppy Montgomery (Carrie Wells)\nDylan Walsh (Al Burns)\nDallas Roberts (Eliot Delson)\nJames Hiroyuki Liao (Jay Lee)\nTawny Cypress (Cherie Rollins-Murray)\nJane Curtin (Joanne Webster)\nBrette Taylor (Eileen Brenner)\nRyan Barry (Harvey Reynolds)\nLarry Pine (Stanton Ward)",
		"ChannelName": "sixx",
		"Start": "2018-09-12T18:28:49+02:00",
		"Stop": "2018-09-12T19:18:51+02:00",
		"Info": {
			"Drehbuch": [
				"Barry Schindel"
			],
			"Regie": [
				"Jan Eliasberg"
			]
		}
	},
	{
		"Title": "Grey's Anatomy - Die jungen Ärzte",
		"Subtitle": "",
		"Summary": "",
		"Description": "Mark Sloan hat sich von Richard anheuern lassen, um die kosmetische Chirurgie zu verstärken. Das stört besonders Addison, die schon längst bereut, ihn für eine heiße \"Frust-Linderungs-Nacht\" nach Seattle geholt zu haben. Derek will Mark sowieso am liebsten auf den Mond schießen, und sogar Alex, der Mark auf professioneller Ebene schätzt, stellt schnell fest, dass er menschlich nicht viel taugt. Indes bricht Meredith mit schweren Bauchschmerzen zusammen ...\n\nRegie: Dan Lerner\nDrehbuch: Allan Heinberg\nAutor: Shonda Rhimes\nKomponist: Danny Lux\nKamera: Herbert Davis\nSchnitt: Briana London, Edward Ornelas\n\nDarsteller:\nEllen Pompeo (Dr. Meredith Grey)\nJustin Chambers (Dr. Alex Karev)\nJames Pickens jr. (Dr. Richard Webber)\nChandra Wilson (Dr. Miranda Bailey)\nPatrick Dempsey (Dr. Derek Shepherd)\nSandra Oh (Dr. Cristina Yang)\nKatherine Heigl (Dr. Isobel \"Izzie\" Stevens)\nT. R. Knight (Dr. George O'Malley)\nIsaiah Washington (Dr. Preston Burke)",
		"ChannelName": "sixx",
		"Start": "2018-09-12T19:18:51+02:00",
		"Stop": "2018-09-12T20:14:45+02:00",
		"Info": {
			"Autor": [
				"Shonda Rhimes"
			],
			"Drehbuch": [
				"Allan Heinberg"
			],
			"Kamera": [
				"Herbert Davis"
			],
			"Komponist": [
				"Danny Lux"
			],
			"Regie": [
				"Dan Lerner"
			],
			"Schnitt": [
				"Briana London",
				"Edward Ornelas"
			]
		}
	},
	{
		"Title": "Paula kommt ... Sexpedition Deutschland",
		"Subtitle": "",
		"Summary": "",
		"Description": "Moderation: Paula Lambert\n\nZusammen mit ihrem Co-Host, Moderator und Kommunikationscoach Lukas Klaschinski, macht sich Sex-Expertin Paula Lambert auf zu einem erotischen Roadtrip quer durch die Republik. Warum geht Frau zum Vulva Watching? Macht täglicher Sex eine Beziehung besser? Wieviel Ehrlichkeit verträgt die Liebe? Und wie steht es eigentlich mit Lukas' \"Fingerfertigkeit\"? Paula Lambert und Lukas Klaschinski geben die Antwort - aus weiblicher und männlicher Perspektive.",
		"ChannelName": "sixx",
		"Start": "2018-09-12T20:14:45+02:00",
		"Stop": "2018-09-12T21:25:05+02:00",
		"Info": {
			"Moderation": [
				"Paula Lambert"
			]
		}
	},
	{
		"Title": "Paula kommt - Sex und Gute Nacktgeschichten",
		"Subtitle": "",
		"Summary": "",
		"Description": "Moderation: Paula Lambert\n\nDie 32-jährige Anett hat sich in den sieben Jahre jüngeren Dustyn verliebt - kein ungewöhnliches Phänomen in der heutigen Zeit. Dustyn schwärmt von dem Selbstbewusstsein seiner Freundin im Bett - sie weiß, wer sie ist und wie sie verführt. Gemeinsam mit Paula diskutieren die Frischverlobten aber auch die Nachteile ihres Altersunterschieds. Und sie verraten, was sie ganz besonders auf Touren bringt ...",
		"ChannelName": "sixx",
		"Start": "2018-09-12T21:25:05+02:00",
		"Stop": "2018-09-12T22:04:52+02:00",
		"Info": {
			"Moderation": [
				"Paula Lambert"
			]
		}
	},
	{
		"Title": "Paula kommt - Sex und Gute Nacktgeschichten",
		"Subtitle": "",
		"Summary": "",
		"Description": "Moderation: Paula Lambert\n\nVanessa und Toni kommen in ihrem Liebesleben voll auf ihre Kosten und probieren gerne Neues miteinander aus. Früher war das unvorstellbar für die korpulente Vanessa: Sie hatte schlechte Erfahrungen mit anderen gemacht und wurde von Selbstzweifeln geplagt. Doch dann traf sie Toni, der ihr die Angst nahm und ihr ihren ersten Orgasmus verschaffte. Allerdings braucht Vanessa Tipps von Paula, was Deep Throat angeht.",
		"ChannelName": "sixx",
		"Start": "2018-09-12T22:04:52+02:00",
		"Stop": "2018-09-12T22:43:17+02:00",
		"Info": {
			"Moderation": [
				"Paula Lambert"
			]
		}
	},
	{
		"Title": "Paula kommt - Sex und Gute Nacktgeschichten",
		"Subtitle": "",
		"Summary": "",
		"Description": "Moderation: Paula Lambert\n\nDie 28-jährige Franzi und ihr Freund Kris führen seit einem Jahr eine offene Beziehung. Für die beiden klappt das wunderbar, allerdings gibt es Regeln: Keine Nummern tauschen, nur mit Kondom und kein Wiedersehen mit dem jeweiligen Sexpartner. Das klingt modern, aber wenig romantisch. Paula findet im Gespräch mit den beiden heraus, wie sehr sie wirklich hinter diesem Beziehungsmodell stehen.",
		"ChannelName": "sixx",
		"Start": "2018-09-12T22:43:17+02:00",
		"Stop": "2018-09-12T23:15:16+02:00",
		"Info": {
			"Moderation": [
				"Paula Lambert"
			]
		}
	},
	{
		"Title": "Paula kommt ... am Telefon",
		"Subtitle": "",
		"Summary": "",
		"Description": "In ihrer neuen Call-In-Show \"Paula kommt ... am Telefon\" beantwortet Sex-Expertin Paula Lambert live die Fragen ihrer Anrufer und spricht mit ihnen über alles, was sie im Kosmos Liebe, Sex und Beziehungen bewegt: von Dating über Eifersucht bis zu Sex-Praktiken und prickelnden Sex-Fantasien. Paula Lambert nimmt kein Blatt vor den Mund und weiß, was Frauen (noch) glücklich(er) macht.",
		"ChannelName": "sixx",
		"Start": "2018-09-12T23:15:16+02:00",
		"Stop": "2018-09-13T00:20:36+02:00",
		"Info": {}
	}
]