[
	{
		"Title": "Supergirl",
		"Subtitle": "",
		"Summary": "",
		"Description": "Selena plant mithilfe von Coville und ihren Ordensschwestern, Reign wiederzubeleben. Damit diese ohne Sam existieren kann, benötigen sie aus dem DEO Blutproben von Pestilence und Purity. Sam fühlt sich indes zunehmend schlechter und fragt Lena und Alex um Rat. Kara, Alura und Mon-El kommen in Argo hinter Selenas tödlichen Plan und müssen einen Weg finden, ihren Freunden auf der Erde zu helfen. Für J'onn rückt der Zeitpunkt immer näher, seinem Vater Lebewohl zu sagen.\n\nRegie: Armen V. Kevorkian\nDrehbuch: Ray Utarnachitt, Cindy Lichtman\nKomponist: Daniel James Chan, Blake Neely\nKamera: James Liston\nSchnitt: Andi Armaganian\n\nDarsteller:\nMelissa Benoist (Kara Danvers / Supergirl)\nMehcad Brooks (James Olsen)\nChyler Leigh (Alex Danvers)\nJeremy Jordan (Winn Schott)\nDavid Harewood (J'onn J'onzz)\nCalista Flockhart (Cat Grant)\nKatie McGrath (Lena Luthor)\nOdette Annable (Samantha Arias / Reign)\nChris Wood (Mon-El)",
		"ChannelName": "sixx",
		"Start": "2018-09-14T00:43:19+02:00",
		"Stop": "2018-09-14T01:23:16+02:00",
		"Info": {
			"Drehbuch": [
				"Ray Utarnachitt",
				"Cindy Lichtman"
			],
			"Kamera": [
				"James Liston"
			],
			"Komponist": [
				"Daniel James Chan",
				"Blake Neely"
			],
			"Regie": [
				"Armen V. Kevorkian"
			],
			"Schnitt": [
				"Andi Armaganian"
			]
		}
	},
	{
		"Title": "Supergirl",
		"Subtitle": "",
		"Summary": "",
		"Description": "Reign ist dabei, aus der Erde ein neues Krypton zu erschaffen. Dafür reist sie zum Erdinneren und verursacht dabei zahlreiche Erdbeben. Sam besucht das Dunkle Tal auf der Suche nach dem \"Brunnen der Lillith\", der ihr Stärke verleihen und sie zu einer ebenbürtigen Gegnerin für Reign machen soll. Im Kampf gegen die Weltenkillerin sterben einige Vertraute von Kara, weshalb diese versucht, die Zeit zurückzudrehen. J'onn übergibt indes die Leitung des DEO an Alex.\n\nRegie: Jesse Warn\nDrehbuch: Robert Rovner, Jessica Queller\nKomponist: Daniel James Chan, Blake Neely\nKamera: Shamus Whiting-Hewlett\nSchnitt: Barbara Gerard\n\nDarsteller:\nMelissa Benoist (Kara Danvers / Supergirl)\nMehcad Brooks (James Olsen)\nChyler Leigh (Alex Danvers)\nJeremy Jordan (Winn Schott)\nDavid Harewood (J'onn J'onzz)\nCalista Flockhart (Cat Grant)\nKatie McGrath (Lena Luthor)\nOdette Annable (Samantha Arias / Reign)\nChris Wood (Mon-El)",
		"ChannelName": "sixx",
		"Start": "2018-09-14T01:23:16+02:00",
		"Stop": "2018-09-14T02:03:17+02:00",
		"Info": {
			"Drehbuch": [
				"Robert Rovner",
				"Jessica Queller"
			],
			"Kamera": [
				"Shamus Whiting-Hewlett"
			],
			"Komponist": [
				"Daniel James Chan",
				"Blake Neely"
			],
			"Regie": [
				"Jesse Warn"
			],
			"Schnitt": [
				"Barbara Gerard"
			]
		}
	}
]