[
	{
		"Title": "Paula kommt ... Sexpedition Deutschland",
		"Subtitle": "",
		"Summary": "",
		"Description": "Moderation: Paula Lambert\n\nZusammen mit ihrem Co-Host, Moderator und Kommunikationscoach Lukas Klaschinski, macht sich Sex-Expertin Paula Lambert auf zu einem erotischen Roadtrip quer durch die Republik. Warum geht Frau zum Vulva Watching? Macht täglicher Sex eine Beziehung besser? Wieviel Ehrlichkeit verträgt die Liebe? Und wie steht es eigentlich mit Lukas' \"Fingerfertigkeit\"? Paula Lambert und Lukas Klaschinski geben die Antwort - aus weiblicher und männlicher Perspektive.",
		"ChannelName": "sixx",
		"Start": "2018-09-13T00:20:36+02:00",
		"Stop": "2018-09-13T01:30:09+02:00",
		"Info": {
			"Moderation": [
				"Paula Lambert"
			]
		}
	},
	{
		"Title": "Paula kommt ... am Telefon",
		"Subtitle": "",
		"Summary": "",
		"Description": "In ihrer neuen Call-In-Show \"Paula kommt ... am Telefon\" beantwortet Sex-Expertin Paula Lambert live die Fragen ihrer Anrufer und spricht mit ihnen über alles, was sie im Kosmos Liebe, Sex und Beziehungen bewegt: von Dating über Eifersucht bis zu Sex-Praktiken und prickelnden Sex-Fantasien. Paula Lambert nimmt kein Blatt vor den Mund und weiß, was Frauen (noch) glücklich(er) macht.",
		"ChannelName": "sixx",
		"Start": "2018-09-13T01:30:09+02:00",
		"Stop": "2018-09-13T02:30:14+02:00",
		"Info": {}
	},
	{
		"Title": "Paula kommt - Sex und Gute Nacktgeschichten",
		"Subtitle": "",
		"Summary": "",
		"Description": "Moderation: Paula Lambert\n\nVanessa und Toni kommen in ihrem Liebesleben voll auf ihre Kosten und probieren gerne Neues miteinander aus. Früher war das unvorstellbar für die korpulente Vanessa: Sie hatte schlechte Erfahrungen mit anderen gemacht und wurde von Selbstzweifeln geplagt. Doch dann traf sie Toni, der ihr die Angst nahm und ihr ihren ersten Orgasmus verschaffte. Allerdings braucht Vanessa Tipps von Paula, was Deep Throat angeht.",
		"ChannelName": "sixx",
		"Start": "2018-09-13T02:30:14+02:00",
		"Stop": "2018-09-13T02:58:57+02:00",
		"Info": {
			"Moderation": [
				"Paula Lambert"
			]
		}
	},
	{
		"Title": "Paula kommt - Sex und Gute Nacktgeschichten",
		"Subtitle": "",
		"Summary": "",
		"Description": "Moderation: Paula Lambert\n\nDie 32-jährige Anett hat sich in den sieben Jahre jüngeren Dustyn verliebt - kein ungewöhnliches Phänomen in der heutigen Zeit. Dustyn schwärmt von dem Selbstbewusstsein seiner Freundin im Bett - sie weiß, wer sie ist und wie sie verführt. Gemeinsam mit Paula diskutieren die Frischverlobten aber auch die Nachteile ihres Altersunterschieds. Und sie verraten, was sie ganz besonders auf Touren bringt ...",
		"ChannelName": "sixx",
		"Start": "2018-09-13T02:58:57+02:00",
		"Stop": "2018-09-13T03:28:14+02:00",
		"Info": {
			"Moderation": [
				"Paula Lambert"
			]
		}
	},
	{
		"Title": "Paula kommt - Sex und Gute Nacktgeschichten",
		"Subtitle": "",
		"Summary": "",
		"Description": "Moderation: Paula Lambert\n\nDie 28-jährige Franzi und ihr Freund Kris führen seit einem Jahr eine offene Beziehung. Für die beiden klappt das wunderbar, allerdings gibt es Regeln: Keine Nummern tauschen, nur mit Kondom und kein Wiedersehen mit dem jeweiligen Sexpartner. Das klingt modern, aber wenig romantisch. Paula findet im Gespräch mit den beiden heraus, wie sehr sie wirklich hinter diesem Beziehungsmodell stehen.",
		"ChannelName": "sixx",
		"Start": "2018-09-13T03:28:14+02:00",
		"Stop": "2018-09-13T03:54:43+02:00",
		"Info": {
			"Moderation": [
				"Paula Lambert"
			]
		}
	},
	{
		"Title": "Paula kommt - Sex und Gute Nacktgeschichten",
		"Subtitle": "",
		"Summary": "",
		"Description": "Moderation: Paula Lambert\n\nDie 43-jährige Trixie hat über 20 Jahre lang als Edelhure ihr Geld gemacht. Der Weg ins Rotlicht war ihre freiwillige Entscheidung. Mittlerweile hat die dreifache Mutter einen extremen Lebenswandel hinter sich: Sie liebt eine Frau und betreibt einen Bio-Laden. Mit Paula bequatscht sie die Anekdoten aus ihrem früheren Leben und erzählt, warum sie dem Milieu den Rücken gekehrt hat.",
		"ChannelName": "sixx",
		"Start": "2018-09-13T03:54:43+02:00",
		"Stop": "2018-09-13T04:23:01+02:00",
		"Info": {
			"Moderation": [
				"Paula Lambert"
			]
		}
	},
	{
		"Title": "Unter Fremden Decken - Auf der Suche nach dem besten Sex der Welt",
		"Subtitle": "",
		"Summary": "",
		"Description": "Oh l'amour! In \"Unter fremden Decken - Auf der Suche nach dem besten Sex der Welt\" gehen die Sex-Experten Paula Lambert und Thilo Mischke auf erotische Mission. Unterwegs in Frankreich, Schweden, Kenia, Brasilien und Japan und mit Blick auf verblüffende \"Sexfacts\" im internationalen Vergleich, wollen Paula und Thilo herausfinden: Wo sind die Menschen mit ihrer Sexualität am glücklichsten - und warum?",
		"ChannelName": "sixx",
		"Start": "2018-09-13T04:23:01+02:00",
		"Stop": "2018-09-13T05:06:21+02:00",
		"Info": {}
	},
	{
		"Title": "sixx QUICKIE",
		"Subtitle": "",
		"Summary": "",
		"Description": "Schnell. Informativ. Unterhaltsam. sixx QUICKIE informiert dich täglich über Aktuelles, Wissenswertes und Skurriles aus den Bereichen Fashion, Beauty, Lifestyle, Stars, Food, Reise, Dating und Sex.",
		"ChannelName": "sixx",
		"Start": "2018-09-13T05:06:21+02:00",
		"Stop": "2018-09-13T05:27:07+02:00",
		"Info": {}
	},
	{
		"Title": "Grey's Anatomy - Die jungen Ärzte",
		"Subtitle": "",
		"Summary": "",
		"Description": "Mark Sloan hat sich von Richard anheuern lassen, um die kosmetische Chirurgie zu verstärken. Das stört besonders Addison, die schon längst bereut, ihn für eine heiße \"Frust-Linderungs-Nacht\" nach Seattle geholt zu haben. Derek will Mark sowieso am liebsten auf den Mond schießen, und sogar Alex, der Mark auf professioneller Ebene schätzt, stellt schnell fest, dass er menschlich nicht viel taugt. Indes bricht Meredith mit schweren Bauchschmerzen zusammen ...\n\nRegie: Dan Lerner\nDrehbuch: Allan Heinberg\nAutor: Shonda Rhimes\nKomponist: Danny Lux\nKamera: Herbert Davis\nSchnitt: Briana London, Edward Ornelas\n\nDarsteller:\nEllen Pompeo (Dr. Meredith Grey)\nJustin Chambers (Dr. Alex Karev)\nJames Pickens jr. (Dr. Richard Webber)\nChandra Wilson (Dr. Miranda Bailey)\nPatrick Dempsey (Dr. Derek Shepherd)\nSandra Oh (Dr. Cristina Yang)\nKatherine Heigl (Dr. Isobel \"Izzie\" Stevens)\nT. R. Knight (Dr. George O'Malley)\nIsaiah Washington (Dr. Preston Burke)",
		"ChannelName": "sixx",
		"Start": "2018-09-13T05:27:07+02:00",
		"Stop": "2018-09-13T06:08:54+02:00",
		"Info": {
			"Autor": [
				"Shonda Rhimes"
			],
			"Drehbuch": [
				"Allan Heinberg"
			],
			"Kamera": [
				"Herbert Davis"
			],
			"Komponist": [
				"Danny Lux"
			],
			"Regie": [
				"Dan Lerner"
			],
			"Schnitt": [
				"Briana London",
				"Edward Ornelas"
			]
		}
	},
	{
		"Title": "Desperate Housewives",
		"Subtitle": "",
		"Summary": "",
		"Description": "Danielle langweilt sich, weil sie nicht das Haus verlassen darf. Als sie aber von der Halloween-Party ihrer Nachbarn hört, scheint sie einen Weg gefunden zu haben, um trotz des Verbotes ihrer Mutter ausgehen zu können. Sie verkleidet sich als ihre Mutter und erscheint so auf der Party. Doch plötzlich platzt ihre Fruchtblase und Danielle überkommt die Angst, dass jemand von ihrem Geheimnis erfahren könnte. Als Adam schließlich zur Geburt geholt wird, verspricht er zu schweigen.\n\nRegie: Larry Shaw\nDrehbuch: Susan Nirah Jaffe, Dahvi Waller\nAutor: Marc Cherry\nKomponist: Steve Jablonsky\nKamera: Eric Van Haren Noman\nSchnitt: Michael Berenbaum, Kaja Fehr, Brent White\n\nDarsteller:\nTeri Hatcher (Susan)\nMarcia Cross (Bree)\nFelicity Huffman (Lynette)\nEva Longoria (Gabrielle)\nBrenda Strong (Mary Alice Young / Erzählerin)\nNicolette Sheridan (Edie Britt)\nJoy Lauren (Danielle Van De Kamp)\nNathan Fillion (Adam Mayfair)\nJames Denton (Mike Delfino)",
		"ChannelName": "sixx",
		"Start": "2018-09-13T06:08:54+02:00",
		"Stop": "2018-09-13T07:03:06+02:00",
		"Info": {
			"Autor": [
				"Marc Cherry"
			],
			"Drehbuch": [
				"Susan Nirah Jaffe",
				"Dahvi Waller"
			],
			"Kamera": [
				"Eric Van Haren Noman"
			],
			"Komponist": [
				"Steve Jablonsky"
			],
			"Regie": [
				"Larry Shaw"
			],
			"Schnitt": [
				"Michael Berenbaum",
				"Kaja Fehr",
				"Brent White"
			]
		}
	},
	{
		"Title": "Charmed - Zauberhafte Hexen",
		"Subtitle": "",
		"Summary": "",
		"Description": "Meerjungfrau Mylie hat ein Abkommen mit einer Meerhexe: Sollte ihr Freund Craig ihr nicht innerhalb von dreißig Tagen eine Liebeserklärung machen, muss sie der Hexe ihre Unsterblichkeit überlassen. Als es immer unwahrscheinlicher wird, dass Craig noch rechtzeitig zu seinen Gefühlen steht, wendet sich Mylie Hilfe suchend an Phoebe. Diese hat allerdings gerade mit eigenen Problemen zu kämpfen: Als sie die Scheidung einreichen wollte, ist Cole plötzlich wieder aufgetaucht ...\n\nRegie: James L. Conway\nDrehbuch: Daniel Cerone\nKomponist: J. Peter Robinson\nKamera: Jonathan West\nSchnitt: Derek Berlatsky\n\nDarsteller:\nAlyssa Milano (Phoebe Halliwell)\nHolly Marie Combs (Piper Halliwell)\nRose McGowan (Paige)\nDorian Gregory (Darryl Morris)\nBrian Krause (Leo)\nJulian McMahon (Cole)\nJaime Pressly (Mylie)\nDan Gauthier (Craig)\nDiane Salinger (Meerhexe)",
		"ChannelName": "sixx",
		"Start": "2018-09-13T07:03:06+02:00",
		"Stop": "2018-09-13T07:59:40+02:00",
		"Info": {
			"Drehbuch": [
				"Daniel Cerone"
			],
			"Kamera": [
				"Jonathan West"
			],
			"Komponist": [
				"J. Peter Robinson"
			],
			"Regie": [
				"James L. Conway"
			],
			"Schnitt": [
				"Derek Berlatsky"
			]
		}
	},
	{
		"Title": "Charmed - Zauberhafte Hexen",
		"Subtitle": "",
		"Summary": "",
		"Description": "Die auf eigenen Wunsch zur Meerjungfrau mutierte Phoebe wird vom Dämon Necron angegriffen, der mit ihrer Hilfe Unsterblichkeit erlangen will. Während des Zweikampfes wird die ehemalige Hexe verletzt und kann gerade noch rechtzeitig mit Leos Hilfe entkommen. Während Phoebe nun zu Hause von ihren Schwestern festgehalten wird, hat der hartnäckige Dämon Necron genug Zeit, einen neuen Plan zu entwickeln. Er will Piper entführen, um Phoebe zu erpressen ...\n\nGaststar: Nancy O'Dell\nRegie: Mel Damski\nDrehbuch: Alison Schapker, Monica Breen\nKomponist: J. Peter Robinson\nKamera: Jonathan West\nSchnitt: Derek Berlatsky\n\nDarsteller:\nAlyssa Milano (Phoebe Halliwell)\nHolly Marie Combs (Piper Halliwell)\nRose McGowan (Paige)\nDorian Gregory (Darryl Morris)\nBrian Krause (Leo)\nJulian McMahon (Cole)\nFinola Hughes (Patty Halliwell)\nJudson Scott (Necron)\nDavid Reivers (Bob Cowan)",
		"ChannelName": "sixx",
		"Start": "2018-09-13T07:59:40+02:00",
		"Stop": "2018-09-13T08:54:56+02:00",
		"Info": {
			"Drehbuch": [
				"Alison Schapker",
				"Monica Breen"
			],
			"Gaststar": [
				"Nancy O'Dell"
			],
			"Kamera": [
				"Jonathan West"
			],
			"Komponist": [
				"J. Peter Robinson"
			],
			"Regie": [
				"Mel Damski"
			],
			"Schnitt": [
				"Derek Berlatsky"
			]
		}
	},
	{
		"Title": "Charmed - Zauberhafte Hexen",
		"Subtitle": "",
		"Summary": "",
		"Description": "Aus Wut darüber, nicht mehr die mächtigste aller Hexen zu sein, nutzt die Märchenhexe die Kraft der Märchen für das Böse. Ihr Ziel ist es, die Halliwells umzubringen und auf diese Weise wieder die stärkste Zauberin zu werden. Als die mächtigen Drei von verschiedensten Märchengestalten angegriffen werden, zögert Piper zunächst aus Angst um ihr ungeborenes Baby, dagegen anzukämpfen. Erst als ihre Schwestern Phoebe und Paige besiegt scheinen, greift sie in das Geschehen ein ...\n\nRegie: John T. Kretchmer\nDrehbuch: Curtis Kheel\nKomponist: Jay Gruska\nKamera: Jonathan West\nSchnitt: Derek Berlatsky\n\nDarsteller:\nAlyssa Milano (Phoebe Halliwell)\nHolly Marie Combs (Piper Halliwell)\nRose McGowan (Paige)\nDorian Gregory (Darryl Morris)\nBrian Krause (Leo)\nJulian McMahon (Cole)\nSean Patrick Flanery (Adam)\nNatalija Nogulich (Märchenhexe)\nJennifer Rhodes (Penny Halliwell)",
		"ChannelName": "sixx",
		"Start": "2018-09-13T08:54:56+02:00",
		"Stop": "2018-09-13T09:51:16+02:00",
		"Info": {
			"Drehbuch": [
				"Curtis Kheel"
			],
			"Kamera": [
				"Jonathan West"
			],
			"Komponist": [
				"Jay Gruska"
			],
			"Regie": [
				"John T. Kretchmer"
			],
			"Schnitt": [
				"Derek Berlatsky"
			]
		}
	},
	{
		"Title": "Charmed - Zauberhafte Hexen",
		"Subtitle": "",
		"Summary": "",
		"Description": "Seit einiger Zeit zieht eine Sirene verheiratete Männer in ihren Bann, um sie vor den Augen ihrer Frauen zu töten und die Witwen im Anschluss zu verbrennen. Als ihr eines Tages Melissa, eine künftige Wächterin des Lichts, ins Netz gerät, kann Cole ihr Opfer gerade noch retten. Der Versuch, die Sirene anschließend im Alleingang zu besiegen, endet in einem Desaster: Cole wird in ihren Bann gezogen und versucht, die ihm zur Rettung eilende Phoebe zu töten ...\n\nRegie: Joel J. Feigenbaum\nDrehbuch: Krista Vernoff\nKomponist: Jay Gruska\nKamera: Jonathan West\nSchnitt: Derek Berlatsky\n\nDarsteller:\nAlyssa Milano (Phoebe Halliwell)\nHolly Marie Combs (Piper Halliwell)\nRose McGowan (Paige)\nDorian Gregory (Darryl Morris)\nBrian Krause (Leo)\nJulian McMahon (Cole)\nMelinda Clarke (Sirene)\nAmy Laughlin (Melissa)\nBranton Boxer (David)",
		"ChannelName": "sixx",
		"Start": "2018-09-13T09:51:16+02:00",
		"Stop": "2018-09-13T10:46:23+02:00",
		"Info": {
			"Drehbuch": [
				"Krista Vernoff"
			],
			"Kamera": [
				"Jonathan West"
			],
			"Komponist": [
				"Jay Gruska"
			],
			"Regie": [
				"Joel J. Feigenbaum"
			],
			"Schnitt": [
				"Derek Berlatsky"
			]
		}
	},
	{
		"Title": "Mein perfektes Hochzeitskleid! - Atlanta",
		"Subtitle": "",
		"Summary": "",
		"Description": "Die Verkaufsberater haben im Laufe ihrer Arbeit schon vieles erlebt, doch eine solch komplizierte Familiendynamik wie bei Braut Kandace haben selbst die abgehärtesten Mitarbeiter noch nicht gesehen.",
		"ChannelName": "sixx",
		"Start": "2018-09-13T10:46:23+02:00",
		"Stop": "2018-09-13T11:40:55+02:00",
		"Info": {}
	},
	{
		"Title": "My Fair Wedding - In drei Wochen zur Traumhochzeit",
		"Subtitle": "",
		"Summary": "",
		"Description": "David Tutera trifft eine Braut, die sich eine Hochzeit im Stil der 20er Jahre wünscht: Kimberly Marrero hat Stil, Anmut und ein traumhaft schönes Kleid. Doch das Outfit ihrer Brautjungfern ist gar nicht nach Davids Geschmack. Für die Feier, für die der Promi-Wedding-Planner sich vom Literaturklassiker \"Der große Gatsby\" inspirieren lässt, müssen neue Kleider, Vintage-Accessoires und eine passende Location her.\n\nExperte: David Tutera",
		"ChannelName": "sixx",
		"Start": "2018-09-13T11:40:55+02:00",
		"Stop": "2018-09-13T12:37:37+02:00",
		"Info": {}
	},
	{
		"Title": "Der Hundeflüsterer",
		"Subtitle": "",
		"Summary": "",
		"Description": "Jeder Hund kann aggressive Verhaltensweisen an den Tag legen, doch es gibt Rassen, die von der Gesellschaft als besonders gefährlich eingestuft werden. Dies beweist auch eine Studie, die von der Redaktion des \"Hundeflüsterers\" in Auftrag gegeben wurde. Cesar Millan besucht heute die aggressivsten Hunde, die er in seiner Laufbahn kennengelernt hat. Kann er die Ergebnisse der Studie doch widerlegen?\n\nCoach: Cesar Millan",
		"ChannelName": "sixx",
		"Start": "2018-09-13T12:37:37+02:00",
		"Stop": "2018-09-13T13:36:13+02:00",
		"Info": {}
	},
	{
		"Title": "Der Hundeflüsterer",
		"Subtitle": "",
		"Summary": "",
		"Description": "Husky-Welpe Spike ist der erste Hund der Familie Rassibi. Vater Josh hat den Hund besonders in Herz geschlossen. Um so trauriger ist er nun, dass Spike nicht mehr mit den Kindern spielen darf und vom Rest der Familie durch eine dicke Glaswand getrennt ist. Er wurde immer hyperaktiver und hat die kleine Tochter Sara bei einem Spaziergang zu Boden geworfen. Kann Cesar helfen, den Hund wieder in die Familie zu integrieren?\n\nCoach: Cesar Millan",
		"ChannelName": "sixx",
		"Start": "2018-09-13T13:36:13+02:00",
		"Stop": "2018-09-13T14:30:36+02:00",
		"Info": {}
	},
	{
		"Title": "Der Hundeflüsterer",
		"Subtitle": "",
		"Summary": "",
		"Description": "Die kleine Gemeinde Moorpark in Kalifornien hat Bilderbuch-Charme: Die Bewohner helfen sich gegenseitig und veranstalten regelmäßig Gartenpartys und Grillabende. Es könnte das perfekte Zusammenleben sein - wären da nicht die Hunde. Drei hyperaktive Huskies, ein kaufreudiger Labrador-Welpe und ein bissiger Mastiff-Mischling sind nur ein paar Problemfälle der insgesamt 15 Hunde, die in der Gemeinde leben. Kann Cesar Ruhe in diesen wilden Haufen bringen?\n\nCoach: Cesar Millan",
		"ChannelName": "sixx",
		"Start": "2018-09-13T14:30:36+02:00",
		"Stop": "2018-09-13T15:29:12+02:00",
		"Info": {}
	},
	{
		"Title": "Sex and the City",
		"Subtitle": "",
		"Summary": "",
		"Description": "Miranda und Steve beschließen, für vier Tage in ein romantisches Hotel zu fahren - den kleinen Brady lassen sie in der Obhut von Carrie und Charlotte. Bald stellt sich Carrie die Frage, ob sie selbst ein Kind haben möchte. Als sie erfährt, dass Aleksandr bereits eine 22-jährige Tochter hat, kommt sie ins Grübeln ... Die dauergestresste Miranda ist indes ganz kribbelig: Nichts weiter zu tun, als im Bett zu liegen und mehrmals am Tag mit Steve Sex zu haben, ist nichts für sie ...\n\nRegie: Michael Engler\nDrehbuch: Cindy Chupack\nAutor: Candace Bushnell\nKomponist: Douglas J. Cuomo, Dan Lieberstein\nKamera: John Thomas\n\nDarsteller:\nSarah Jessica Parker (Carrie Bradshaw)\nKim Cattrall (Samantha Jones)\nKristin Davis (Charlotte York)\nCynthia Nixon (Miranda Hobbes)\nDavid Eigenberg (Steve Brady)\nMikhail Baryshnikov (Aleksandr Petrovsky)\nJulia Sweeney (Amy)\nDavid Deblinger (Dr. Pinkner)\nVictoria Valero",
		"ChannelName": "sixx",
		"Start": "2018-09-13T15:29:12+02:00",
		"Stop": "2018-09-13T16:03:59+02:00",
		"Info": {
			"Autor": [
				"Candace Bushnell"
			],
			"Drehbuch": [
				"Cindy Chupack"
			],
			"Kamera": [
				"John Thomas"
			],
			"Komponist": [
				"Douglas J. Cuomo",
				"Dan Lieberstein"
			],
			"Regie": [
				"Michael Engler"
			]
		}
	},
	{
		"Title": "Sex and the City",
		"Subtitle": "",
		"Summary": "",
		"Description": "Für Samantha beginnt die Chemotherapie. Das Grauen ist perfekt, als sie in einem sehr intimen Moment Haare zu verlieren beginnt. Carrie ist indes überrascht, wie sehr sie Sams Krankheit mitnimmt. Als Aleksandr unsensibel reagiert, rastet Carrie aus. Nachdem Charlottes und Harrys Versuche, ein Baby zu bekommen, wieder einmal gescheitert sind, ist Charlotte der Verzweiflung nahe. Beim Joggen im Park macht sie die Bekanntschaft einer kleinen Hundedame namens Elizabeth Taylor ...\n\nRegie: Michael Engler\nDrehbuch: Jenny Bicks\nAutor: Candace Bushnell\nKomponist: Douglas J. Cuomo, Dan Lieberstein\nKamera: John Thomas\n\nDarsteller:\nSarah Jessica Parker (Carrie Bradshaw)\nKim Cattrall (Samantha Jones)\nKristin Davis (Charlotte York)\nCynthia Nixon (Miranda Hobbes)\nDana Ivey (Trudy Stork)\nMikhail Baryshnikov (Aleksandr Petrovsky)\nDavid Eigenberg (Steve Brady)\nEvan Handler (Harry Goldenblatt)\nJonathan Hadary (Vincent)",
		"ChannelName": "sixx",
		"Start": "2018-09-13T16:03:59+02:00",
		"Stop": "2018-09-13T16:38:37+02:00",
		"Info": {
			"Autor": [
				"Candace Bushnell"
			],
			"Drehbuch": [
				"Jenny Bicks"
			],
			"Kamera": [
				"John Thomas"
			],
			"Komponist": [
				"Douglas J. Cuomo",
				"Dan Lieberstein"
			],
			"Regie": [
				"Michael Engler"
			]
		}
	},
	{
		"Title": "Desperate Housewives",
		"Subtitle": "",
		"Summary": "",
		"Description": "Als Victor sie bittet, ein Wochenende mit ihm auf dem Boot zu verbringen, ist Gabrielle zunächst begeistert. Doch dann erfährt sie von Carlos, dass Victor über ihre Affäre Bescheid weiß. Sie bekommt Angst und stößt ihn völlig unüberlegt über Bord. Als Susan Mike auf Betäubungstabletten anspricht, die er in letzter Zeit häufiger zu sich nimmt, beteuert er, nicht darauf angewiesen zu sein, und wirft sie in den Ausguss. Doch er ist nicht umsonst Klempner ...\n\nRegie: David Warren\nDrehbuch: Chuck Ranberg, Anne Flett-Giordano\nAutor: Marc Cherry\nKomponist: Steve Jablonsky\nKamera: Lowell Peterson\nSchnitt: Andrew Doerfer\n\nDarsteller:\nTeri Hatcher (Susan)\nMarcia Cross (Bree)\nFelicity Huffman (Lynette)\nEva Longoria (Gabrielle)\nBrenda Strong (Mary Alice Young / Erzählerin)\nNicolette Sheridan (Edie Britt)\nJames Denton (Mike Delfino)\nJohn Slattery (Victor Lang)\nRicardo Antonio Chavira (Carlos Solis)",
		"ChannelName": "sixx",
		"Start": "2018-09-13T16:38:37+02:00",
		"Stop": "2018-09-13T17:33:36+02:00",
		"Info": {
			"Autor": [
				"Marc Cherry"
			],
			"Drehbuch": [
				"Chuck Ranberg",
				"Anne Flett-Giordano"
			],
			"Kamera": [
				"Lowell Peterson"
			],
			"Komponist": [
				"Steve Jablonsky"
			],
			"Regie": [
				"David Warren"
			],
			"Schnitt": [
				"Andrew Doerfer"
			]
		}
	},
	{
		"Title": "Cold Case - Kein Opfer ist je vergessen",
		"Subtitle": "",
		"Summary": "",
		"Description": "Ein Krankenpfleger hat sich in mehreren Fällen der Euthanasie schuldig gemacht. In der Gerichtsmedizin werden daraufhin alle Todesfälle aus seiner Dienstzeit überprüft. Lilly Rush stößt auf die Akte von Jay Dratton. Bei ihm wurde 1998 ein bösartiger, nicht operabler Gehirntumor diagnostiziert. Es stellt sich heraus, dass sein Tod durch eine Überdosis Morphium vorzeitig herbeigeführt wurde. Privat leidet Rush unter der Alkoholsucht ihrer schwerkranken Mutter ...\n\nRegie: Paris Barclay\nDrehbuch: Gavin Harris\nKomponist: Michael A. Levine\nKamera: Donald E. Thorin jr.\n\nDarsteller:\nKathryn Morris (Det. Lilly Rush)\nDanny Pino (Det. Scott Valens)\nJohn Finn (Lt. John Stillman)\nJeremy Ratchford (Det. Nick Vera)\nThom Barry (Det. Will Jeffries)\nAnthony Starke (Jay Dratton)\nMeredith Baxter (Ellen Rush)\nLynda Boyd (Caroline Dratton)\nTracie Thoms (Kat Miller)",
		"ChannelName": "sixx",
		"Start": "2018-09-13T17:33:36+02:00",
		"Stop": "2018-09-13T18:29:31+02:00",
		"Info": {
			"Drehbuch": [
				"Gavin Harris"
			],
			"Kamera": [
				"Donald E. Thorin jr."
			],
			"Komponist": [
				"Michael A. Levine"
			],
			"Regie": [
				"Paris Barclay"
			]
		}
	},
	{
		"Title": "Unforgettable",
		"Subtitle": "",
		"Summary": "",
		"Description": "Carrie, Eliot und Joanne sind auf einer Veranstaltung des Bürgermeisters Beverly eingeladen, als Beverly, Eliot und der Immobilien-Mogul Ron Skinner in einem Fahrstuhl eingeschlossen werden. Unbekannte haben das Gebäude unter ihrer Kontrolle, sie drohen den Aufzug abstürzen zu lassen und halten die übrigen Gäste als Geiseln. Während Carrie, die von den Tätern unentdeckt blieb, im Gebäude versucht, Schlimmeres zu verhindern, übernimmt Al außerhalb die Ermittlungen.\n\nRegie: Rick Bota\nDrehbuch: Spencer Hudnut\nKomponist: Jacob Groth\n\nDarsteller:\nPoppy Montgomery (Carrie Wells)\nDylan Walsh (Al Burns)\nDallas Roberts (Eliot Delson)\nJames Hiroyuki Liao (Jay Lee)\nJane Curtin (Joanne Webster)\nTawny Cypress (Cherie Rollins-Murray)\nFrankie Faison (Bürgermeister Beverly)\nNick Chinlund (Ron Skinner)\nKelly AuCoin (Jonathan \"Alpha Omega\" Brody)",
		"ChannelName": "sixx",
		"Start": "2018-09-13T18:29:31+02:00",
		"Stop": "2018-09-13T19:19:21+02:00",
		"Info": {
			"Drehbuch": [
				"Spencer Hudnut"
			],
			"Komponist": [
				"Jacob Groth"
			],
			"Regie": [
				"Rick Bota"
			]
		}
	},
	{
		"Title": "Grey's Anatomy - Die jungen Ärzte",
		"Subtitle": "",
		"Summary": "",
		"Description": "Beziehungsprobleme dominieren weiterhin Dereks Alltag. Die Scheidung von Addison scheint glatt über die Bühne zu gehen, weil er alle Schuld auf sich nimmt und Addison allen Besitz überlassen will. Doch sie muss ihm schließlich gestehen, dass Mark nicht nur ein One-Night-Stand war, sondern eine wirkliche, wenn auch kurzlebige Beziehung. Als Meredith ihm sagt, sie habe sich von Finn getrennt, kann er erst einmal gar nicht reagieren ...\n\nRegie: Jeffrey Melman\nDrehbuch: Zoanne Clack, Tony Phelan, Joan Rater\nAutor: Shonda Rhimes\nKomponist: Danny Lux\nKamera: Herbert Davis\nSchnitt: Briana London, Edward Ornelas, Susan Vaill\n\nDarsteller:\nEllen Pompeo (Dr. Meredith Grey)\nJustin Chambers (Dr. Alex Karev)\nJames Pickens jr. (Dr. Richard Webber)\nChandra Wilson (Dr. Miranda Bailey)\nPatrick Dempsey (Dr. Derek Shepherd)\nSandra Oh (Dr. Cristina Yang)\nKatherine Heigl (Dr. Isobel \"Izzie\" Stevens)\nT. R. Knight (Dr. George O'Malley)\nIsaiah Washington (Dr. Preston Burke)",
		"ChannelName": "sixx",
		"Start": "2018-09-13T19:19:21+02:00",
		"Stop": "2018-09-13T20:14:45+02:00",
		"Info": {
			"Autor": [
				"Shonda Rhimes"
			],
			"Drehbuch": [
				"Zoanne Clack",
				"Tony Phelan",
				"Joan Rater"
			],
			"Kamera": [
				"Herbert Davis"
			],
			"Komponist": [
				"Danny Lux"
			],
			"Regie": [
				"Jeffrey Melman"
			],
			"Schnitt": [
				"Briana London",
				"Edward Ornelas",
				"Susan Vaill"
			]
		}
	},
	{
		"Title": "Supergirl",
		"Subtitle": "",
		"Summary": "",
		"Description": "Selena plant mithilfe von Coville und ihren Ordensschwestern, Reign wiederzubeleben. Damit diese ohne Sam existieren kann, benötigen sie aus dem DEO Blutproben von Pestilence und Purity. Sam fühlt sich indes zunehmend schlechter und fragt Lena und Alex um Rat. Kara, Alura und Mon-El kommen in Argo hinter Selenas tödlichen Plan und müssen einen Weg finden, ihren Freunden auf der Erde zu helfen. Für J'onn rückt der Zeitpunkt immer näher, seinem Vater Lebewohl zu sagen.\n\nRegie: Armen V. Kevorkian\nDrehbuch: Ray Utarnachitt, Cindy Lichtman\nKomponist: Daniel James Chan, Blake Neely\nKamera: James Liston\nSchnitt: Andi Armaganian\n\nDarsteller:\nMelissa Benoist (Kara Danvers / Supergirl)\nMehcad Brooks (James Olsen)\nChyler Leigh (Alex Danvers)\nJeremy Jordan (Winn Schott)\nDavid Harewood (J'onn J'onzz)\nCalista Flockhart (Cat Grant)\nKatie McGrath (Lena Luthor)\nOdette Annable (Samantha Arias / Reign)\nChris Wood (Mon-El)",
		"ChannelName": "sixx",
		"Start": "2018-09-13T20:14:45+02:00",
		"Stop": "2018-09-13T21:05:52+02:00",
		"Info": {
			"Drehbuch": [
				"Ray Utarnachitt",
				"Cindy Lichtman"
			],
			"Kamera": [
				"James Liston"
			],
			"Komponist": [
				"Daniel James Chan",
				"Blake Neely"
			],
			"Regie": [
				"Armen V. Kevorkian"
			],
			"Schnitt": [
				"Andi Armaganian"
			]
		}
	},
	{
		"Title": "Supergirl",
		"Subtitle": "",
		"Summary": "",
		"Description": "Reign ist dabei, aus der Erde ein neues Krypton zu erschaffen. Dafür reist sie zum Erdinneren und verursacht dabei zahlreiche Erdbeben. Sam besucht das Dunkle Tal auf der Suche nach dem \"Brunnen der Lillith\", der ihr Stärke verleihen und sie zu einer ebenbürtigen Gegnerin für Reign machen soll. Im Kampf gegen die Weltenkillerin sterben einige Vertraute von Kara, weshalb diese versucht, die Zeit zurückzudrehen. J'onn übergibt indes die Leitung des DEO an Alex.\n\nRegie: Jesse Warn\nDrehbuch: Robert Rovner, Jessica Queller\nKomponist: Daniel James Chan, Blake Neely\nKamera: Shamus Whiting-Hewlett\nSchnitt: Barbara Gerard\n\nDarsteller:\nMelissa Benoist (Kara Danvers / Supergirl)\nMehcad Brooks (James Olsen)\nChyler Leigh (Alex Danvers)\nJeremy Jordan (Winn Schott)\nDavid Harewood (J'onn J'onzz)\nCalista Flockhart (Cat Grant)\nKatie McGrath (Lena Luthor)\nOdette Annable (Samantha Arias / Reign)\nChris Wood (Mon-El)",
		"ChannelName": "sixx",
		"Start": "2018-09-13T21:05:52+02:00",
		"Stop": "2018-09-13T22:08:23+02:00",
		"Info": {
			"Drehbuch": [
				"Robert Rovner",
				"Jessica Queller"
			],
			"Kamera": [
				"Shamus Whiting-Hewlett"
			],
			"Komponist": [
				"Daniel James Chan",
				"Blake Neely"
			],
			"Regie": [
				"Jesse Warn"
			],
			"Schnitt": [
				"Barbara Gerard"
			]
		}
	},
	{
		"Title": "The Originals",
		"Subtitle": "",
		"Summary": "",
		"Description": "Vincent ist im Besitz eines Buches, mit dessen Hilfe er Inadus Mutter im Reich der Toten finden kann. Sie ist die Einzige, die weiß, wie ihre Tochter zu besiegen ist. Das Buch wird Vincent jedoch von seinen Feinden aus der Hand gerissen. Nun sieht er nur noch eine Möglichkeit: Er muss sich selber töten, um ins Reich der Toten zu gelangen. Unterdessen hat Hayley eine furchtbare Vermutung: Hat das Hollow Besitz von ihrer Tochter ergriffen?\n\nRegie: Michael Grossman\nDrehbuch: Michelle Paradise\n\nDarsteller:\nJoseph Morgan (Klaus Mikaelson)\nDaniel Gillies (Elijah Mikaelson)\nPhoebe Tonkin (Hayley)\nCharles Michael Davis (Marcel Gerard)\nYusuf Gatewood (Vincent Griffith)\nRiley Voelkel (Freya Mikaelson)\nClaire Holt (Rebekah Mikaelson)\nSummer Fontana (Hope Mikaelson / The Hollow)\nTaylor Cole (Sofya Voronova)",
		"ChannelName": "sixx",
		"Start": "2018-09-13T22:08:23+02:00",
		"Stop": "2018-09-13T23:02:25+02:00",
		"Info": {
			"Drehbuch": [
				"Michelle Paradise"
			],
			"Regie": [
				"Michael Grossman"
			]
		}
	},
	{
		"Title": "The Originals",
		"Subtitle": "",
		"Summary": "",
		"Description": "Vincent hat eine Idee, wie er Hope vor dem Hollow retten kann. Er kann die böse Macht aus dem Mädchen herausziehen, muss sie aber danach auf vier Menschen verteilen: Klaus, Elijah, Rebekkah und Kol. Um zu vermeiden, dass das Hollow wieder aufersteht, dürfen sich die Geschwister einander nicht nähern. Auch Klaus dürfte seine Tochter Hope nach der Übertragung nie wiedersehen. Er ist aber bereit, dieses Opfer zu bringen - für das Leben seines einzigen Kindes.\n\nRegie: Bethany Rooney\nDrehbuch: Michael Narducci\n\nDarsteller:\nJoseph Morgan (Klaus Mikaelson)\nDaniel Gillies (Elijah Mikaelson)\nPhoebe Tonkin (Hayley)\nCharles Michael Davis (Marcel Gerard)\nYusuf Gatewood (Vincent Griffith)\nRiley Voelkel (Freya Mikaelson)\nClaire Holt (Rebekah Mikaelson)\nNathaniel Buzolic (Kol Mikaelson)\nSummer Fontana (Hope Mikaelson)",
		"ChannelName": "sixx",
		"Start": "2018-09-13T23:02:25+02:00",
		"Stop": "2018-09-13T23:52:03+02:00",
		"Info": {
			"Drehbuch": [
				"Michael Narducci"
			],
			"Regie": [
				"Bethany Rooney"
			]
		}
	},
	{
		"Title": "Vampire Diaries",
		"Subtitle": "",
		"Summary": "",
		"Description": "Jeremy packt seine Koffer, um die Stadt zu verlassen. Als Elena Bonnie erzählt, dass er von Damon manipuliert wurde, ist Bonnie ihr böse. Damon und Stefan töten währenddessen weitere Hybriden. Stefan beschließt, Klaus mit einer List in die Enge zu treiben. Er verlangt von ihm, die Hybriden aus der Stadt zu schaffen, ehe er ihm die Särge zurückgibt. Als Klaus sich nicht darauf einlässt, benutzt Stefan Elena als Druckmittel, indem er droht, sie in einen Vampir zu verwandeln ...\n\nRegie: Wendey Stanzler\nDrehbuch: Kevin Williamson\nKomponist: Michael Suby\nKamera: Dave Perkal\n\nDarsteller:\nNina Dobrev (Elena Gilbert)\nPaul Wesley (Stefan Salvatore)\nIan Somerhalder (Damon Salvatore)\nSteven R. McQueen (Jeremy Gilbert)\nJoseph Morgan (Klaus)\nCandice Accola (Caroline Forbes)\nMatthew Davis (Alaric Saltzman)\nMichael Trevino (Tyler Lockwood)\nZach Roerig (Matt Donovan)",
		"ChannelName": "sixx",
		"Start": "2018-09-13T23:52:03+02:00",
		"Stop": "2018-09-14T00:43:19+02:00",
		"Info": {
			"Drehbuch": [
				"Kevin Williamson"
			],
			"Kamera": [
				"Dave Perkal"
			],
			"Komponist": [
				"Michael Suby"
			],
			"Regie": [
				"Wendey Stanzler"
			]
		}
	}
]