[
	{
		"Title": "Abenteuer Leben täglich",
		"Subtitle": "",
		"Summary": "",
		"Description": "Moderation: Seraphina Kalze\n\nFernsehkoch Dirk Hoffmann war mal wieder auf Tour. Diesmal hat es ihn in ein ganz besonderes Land verschlagen. Ein Land, in dem nicht nur das Essen ein Schmelztiegel aus den verschiedensten Kulturen und Religionen der Welt bildet. Die Rede ist von Israel. Neben Restaurants und Imbissen in den Metropolen Tel Aviv und Jerusalem besucht er unter anderem auch das älteste Kibbuz im Land und bekommt es mit einem Juror der bekanntesten Kochshow Israels zu tun.",
		"ChannelName": "kabel eins",
		"Start": "2018-09-10T16:56:39+02:00",
		"Stop": "2018-09-10T17:55:43+02:00",
		"Info": {
			"Moderation": [
				"Seraphina Kalze"
			]
		}
	},
	{
		"Title": "Mein Lokal, Dein Lokal - Der Profi kommt",
		"Subtitle": "",
		"Summary": "",
		"Description": "Mike Süsser darf sich auf eine spannende Woche in seiner Wahl-Heimat Österreich freuen: Stil, Chic und Eleganz verspricht die Stadt Wien. Im ersten Bezirk öffnet Gastgeber Roberto d'Atri seine Türen und setzt die Messlatte für die Woche hoch oben an. Das Restaurant \"Il Melograno\" befindet sich mitten im historischen Kern der Stadt und bietet stilvolles Ambiente mit anspruchsvoller Küche.\n\nGastgeber: Mike Süsser",
		"ChannelName": "kabel eins",
		"Start": "2018-09-10T17:55:43+02:00",
		"Stop": "2018-09-10T18:55:53+02:00",
		"Info": {}
	},
	{
		"Title": "Gekauft, gekocht, gewonnen",
		"Subtitle": "",
		"Summary": "",
		"Description": "Heute treten die zwei Kochprofis Mario Kotaska und Timo Hinkelmann gegeneinander an. Bereits zu Beginn der Suche nach einem passenden Kandidaten schenken die zwei sich nichts. Timo muss Steinbeißerfilet, Schlagsahne und Beeren verarbeiten; Mario hingegen hat Mango-Chutney, Kartoffeln und Putenbrust zur Verfügung.\n\nKoch: Frank Rosin",
		"ChannelName": "kabel eins",
		"Start": "2018-09-10T18:55:53+02:00",
		"Stop": "2018-09-10T20:14:15+02:00",
		"Info": {}
	},
	{
		"Title": "X-Men 2",
		"Subtitle": "",
		"Summary": "",
		"Description": "Die X-Men sind zurück - und stehen vor einer schwierigen Aufgabe: Nachdem auf den Präsidenten ein Attentat verübt wird, fordert General Stryker ein Anti-Mutanten-Programm. Bald wird Wolverine, Storm und Jean Grey klar, dass nicht ihr Erzfeind Magneto hinter der Tat steckt, sondern Stryker selbst. Sein Ziel: Er will alle Mutanten vernichten und die Weltherrschaft an sich reißen. Den X-Men bleibt nichts anderes übrig, als sich mit Magneto zu verbünden ...\n\nRegie: Bryan Singer\nDrehbuch: Zak Penn, David Hayter, Bryan Singer\nKomponist: John Ottman\nKamera: Newton Thomas Sigel\nSchnitt: John Ottman\n\nDarsteller:\nPatrick Stewart (Professor Charles Xavier)\nHugh Jackman (Logan / Wolverine)\nIan McKellen (Eric Lensherr / Magneto)\nHalle Berry (Ororo Munroe / Storm)\nFamke Janssen (Jean Grey)\nJames Marsden (Scott Summers / Cyclops)\nRebecca Romijn-Stamos (Raven Darkholme / Mystique)\nAnna Paquin (Marie / Rogue)\nBrian Cox (William Stryker)",
		"ChannelName": "kabel eins",
		"Start": "2018-09-10T20:14:15+02:00",
		"Stop": "2018-09-10T22:56:30+02:00",
		"Info": {
			"Drehbuch": [
				"Zak Penn",
				"David Hayter",
				"Bryan Singer"
			],
			"Kamera": [
				"Newton Thomas Sigel"
			],
			"Komponist": [
				"John Ottman"
			],
			"Regie": [
				"Bryan Singer"
			],
			"Schnitt": [
				"John Ottman"
			]
		}
	},
	{
		"Title": "Predator",
		"Subtitle": "",
		"Summary": "",
		"Description": "Arnold Schwarzenegger lässt in diesem Klassiker im Kampf gegen ein Alien die Muskeln spielen: Major Dutch Schaefer und seine Kampftruppe sollen im Dschungel Gefangene aus den Händen der Guerilleros befreien. Doch Dutch stellt bald fest, dass es nicht die Rebellen sind, die seine Elite-Truppe unerbittlich dezimieren. Er hat es mit einem unsichtbaren, blutgierigen Feind zu tun - einem Raubtier aus einer anderen Welt. Er beschließt, den Kampf aufnehmen.\n\nRegie: John McTiernan\nDrehbuch: John G. Thomas, Jim Thomas\nKomponist: Alan Silvestri\nKamera: Donald M. McAlpine\nSchnitt: John F. Link, Mark Helfrich\n\nDarsteller:\nArnold Schwarzenegger (Dutch Schaefer)\nCarl Weathers (Dillon)\nElpidia Carrillo (Anna)\nBill Duke (Mac)\nJesse Ventura (Blain)\nSonny Landham (Billy)\nRichard Chaves (Poncho)\nR. G. Armstrong (Gen. Phillips)\nKevin Peter Hall (Predator)",
		"ChannelName": "kabel eins",
		"Start": "2018-09-10T22:56:30+02:00",
		"Stop": "2018-09-11T00:54:58+02:00",
		"Info": {
			"Drehbuch": [
				"John G. Thomas",
				"Jim Thomas"
			],
			"Kamera": [
				"Donald M. McAlpine"
			],
			"Komponist": [
				"Alan Silvestri"
			],
			"Regie": [
				"John McTiernan"
			],
			"Schnitt": [
				"John F. Link",
				"Mark Helfrich"
			]
		}
	}
]