[
	{
		"Title": "Lethal Weapon",
		"Subtitle": "",
		"Summary": "",
		"Description": "Der Ex-Navy-Seal Chad Jackson bewirbt sich bei einem Juwelier als Sicherheitsmann - und verwüstet den Laden, als er die Stelle nicht bekommt. Kurz darauf rastet er in einer Drogerie aus. Riggs und Murtaugh erfahren von Jacksons Psychiater, dass er unter einer Posttraumatischen Belastungsstörung leidet und Antidepressiva einnimmt. Doch die Pillen, die ihm verschrieben wurden, stimmen mit keinem zugelassenen Medikament überein. Riggs und Murtaugh werden hellhörig ...\n\nRegie: Larry Teng\nDrehbuch: Seamus Kevin Fahey\nKomponist: Ben Decter, Josh Kramon\nKamera: Andrew Strahorn\nSchnitt: Matt Barber\n\nDarsteller:\nDamon Wayans (Roger Murtaugh)\nClayne Crawford (Martin Riggs)\nKeesha Sharp (Trish Murtaugh)\nJordana Brewster (Dr. Maureen \"Mo\" Cahill)\nKevin Rahm (Captain Avery Brooks)\nChandler Kinney (Riana Murtaugh)\nJonathan Fernandez (Scorsese)\nMichael Raymond-James (Chad Jackson)\nArnell Powell (Dr. Nathan Cox)",
		"ChannelName": "kabel eins",
		"Start": "2018-09-16T00:00:57+02:00",
		"Stop": "2018-09-16T00:53:18+02:00",
		"Info": {
			"Drehbuch": [
				"Seamus Kevin Fahey"
			],
			"Kamera": [
				"Andrew Strahorn"
			],
			"Komponist": [
				"Ben Decter",
				"Josh Kramon"
			],
			"Regie": [
				"Larry Teng"
			],
			"Schnitt": [
				"Matt Barber"
			]
		}
	},
	{
		"Title": "Hawaii Five-0",
		"Subtitle": "",
		"Summary": "",
		"Description": "Der Hacker Zack wird kurz nach seiner Freilassung aus dem Gefängnis ermordet. Offenbar ging es um brisante Informationen, die in seinem Besitz waren. Das Five-0-Team tappt im Dunkeln, doch dann gelingt es Kono, auf der Trauerfeier für Zack, das Passwort für dessen Computer zu entwenden. Allerdings wird die Lage dort schnell brenzlig, denn Kriminelle nehmen sämtliche Trauergäste als Geiseln ...\n\nRegie: Larry Teng\nDrehbuch: Mike Schaub\n\nDarsteller:\nAlex O'Loughlin (Steve McGarrett)\nScott Caan (Danny \"Danno\" Williams)\nDaniel Dae Kim (Chin Ho Kelly)\nGrace Park (Kono Kalakaua)\nMatt Bush (Zack Slater)\nAlan Ruck (Mr. Slater)\nMelinda McGraw (Patricia Slater)\nChristine Lahti (Doris McGarrett)\nShelley Berman (Morty Sapperstein)",
		"ChannelName": "kabel eins",
		"Start": "2018-09-16T00:53:18+02:00",
		"Stop": "2018-09-16T01:44:02+02:00",
		"Info": {
			"Drehbuch": [
				"Mike Schaub"
			],
			"Regie": [
				"Larry Teng"
			]
		}
	},
	{
		"Title": "Scorpion",
		"Subtitle": "",
		"Summary": "",
		"Description": "Richard Elia hat sich von seinen Ingenieuren Walters frei zur Verfügung gestellten Raketenantrieb in seine Rakete einbauen lassen. Als ein Fehler auftaucht, macht sich Walter sogleich an die Reparatur. Dummerweise nimmt er dabei den Funkknopf aus dem Ohr und hört die Warnung seines Teams bezüglich eines Unwetters nicht. Ein Blitzeinschlag führt schließlich dazu, dass die Rakete unkontrolliert startet - mit ihm an Bord ...\n\nRegie: Sanford Bookstaver\nDrehbuch: Scott Sullivan, Nick Santora\nKomponist: Tony Morales, Brian Tyler\nKamera: Ken Glassing\nSchnitt: Chad Mochrie\n\nDarsteller:\nElyes Gabel (Walter O'Brien)\nKatharine McPhee (Paige Dineen)\nRobert Patrick (Cabe Gallo)\nEddie Kaye Thomas (Toby Curtis)\nJadyn Wong (Happy Quinn)\nAri Stidham (Sylvester Dodd)\nKevin Weisman (Ray Spiewack)\nAndy Buckley (Elia)\nScott Porter (Tim Armstrong)",
		"ChannelName": "kabel eins",
		"Start": "2018-09-16T01:44:02+02:00",
		"Stop": "2018-09-16T02:31:52+02:00",
		"Info": {
			"Drehbuch": [
				"Scott Sullivan",
				"Nick Santora"
			],
			"Kamera": [
				"Ken Glassing"
			],
			"Komponist": [
				"Tony Morales",
				"Brian Tyler"
			],
			"Regie": [
				"Sanford Bookstaver"
			],
			"Schnitt": [
				"Chad Mochrie"
			]
		}
	}
]