[
	{
		"Title": "The Dark Knight",
		"Subtitle": "",
		"Summary": "",
		"Description": "Oscar-Preisträger Heath Ledger versucht, Gotham City ins Chaos zu stürzen: Die Tage des organisierten Verbrechens in Gotham City scheinen dank Batman und Lt. Gordon gezählt zu sein. In Staatsanwalt Harvey Dent finden die beiden einen weiteren starken Verbündeten. Da der Gesetzeshüter die Gangster gleich reihenweise hinter Gitter bringt, gilt er bereits als der \"weiße Ritter\" der Stadt. Doch urplötzlich taucht mit dem \"Joker\" ein neuer, gefährlicher Gegenspieler auf ...\n\nRegie: Christopher Nolan\nDrehbuch: Jonathan Nolan, Christopher Nolan\nKomponist: James Newton Howard, Hans Zimmer\nKamera: Wally Pfister\nSchnitt: Lee Smith\n\nDarsteller:\nChristian Bale (Bruce Wayne/Batman)\nHeath Ledger (Joker)\nAaron Eckhart (Harvey Dent/Two-Face)\nMichael Caine (Alfred Pennyworth)\nMaggie Gyllenhaal (Rachel Dawes)\nGary Oldman (James Gordon)\nMorgan Freeman (Lucius Fox)\nMonique Gabriela Curnen (Det. Anna Ramirez)\nCilian Murphy (Jonathan Crane/The Scarecrow)",
		"ChannelName": "ProSieben",
		"Start": "2018-09-16T01:53:31+02:00",
		"Stop": "2018-09-16T04:32:51+02:00",
		"Info": {
			"Drehbuch": [
				"Jonathan Nolan",
				"Christopher Nolan"
			],
			"Kamera": [
				"Wally Pfister"
			],
			"Komponist": [
				"James Newton Howard",
				"Hans Zimmer"
			],
			"Regie": [
				"Christopher Nolan"
			],
			"Schnitt": [
				"Lee Smith"
			]
		}
	}
]