[
	{
		"Title": "MacGyver",
		"Subtitle": "",
		"Summary": "",
		"Description": "Ein alter Bekannter von Jack und Matty ist plötzlich wieder auf der Bildfläche aufgetaucht: Emil Beck, ein ehemaliger Regierungsangestellter, der vor vielen Jahren Geheiminformationen stahl und danach untergetaucht ist. Das Team soll Beck nun schnappen, doch der ist seinen Verfolgern scheinbar immer einen Schritt voraus. Noch dazu hat es Mama Coltons Kopfgeldjäger-Truppe ebenfalls auf den lukrativen Fang abgesehen und macht Mac und Co. das Leben schwer.\n\nRegie: Antonio Negret\nDrehbuch: Lindsey Allen\nKomponist: Keith Power\nKamera: Michael Martinez\nSchnitt: Evan Warner\n\nDarsteller:\nLucas Till (Angus MacGyver)\nGeorge Eads (Jack Dalton)\nTristin Mays (Riley Davis)\nJustin Hires (Wilt Bozer)\nMeredith Eaton (Matty Webber)\nLance Gross (Billy Colton)\nJavicia Leslie (Jesse Colton)\nJesse Luken (Owen Palmer)\nRobert Catrini (Lawrence Rowell)",
		"ChannelName": "SAT.1",
		"Start": "2018-09-11T00:49:15+02:00",
		"Stop": "2018-09-11T01:30:00+02:00",
		"Info": {
			"Drehbuch": [
				"Lindsey Allen"
			],
			"Kamera": [
				"Michael Martinez"
			],
			"Komponist": [
				"Keith Power"
			],
			"Regie": [
				"Antonio Negret"
			],
			"Schnitt": [
				"Evan Warner"
			]
		}
	},
	{
		"Title": "MacGyver",
		"Subtitle": "",
		"Summary": "",
		"Description": "Dawn sitzt völlig aufgelöst in Jacks Wohnung. Ihr Chef bei der CIA kam bei einem Autounfall ums Leben, sie vermutet allerdings Mord: Kurz vor seinem Tod hatte ihr Paul erzählt, dass jemand von der CIA offenbar falsche Pässe ausstellt, um Menschen illegal ins Land zu holen. Phoenix geht der Sache nach und stellt fest, dass Dawns Vermutung richtig war. Nun müssen nicht nur die illegal Eingeschleusten gefunden, sondern auch der Maulwurf enttarnt werden - ein riskantes Unterfangen.\n\nRegie: Sharat Raju\nDrehbuch: Andrew Karlsruher\nKomponist: Keith Power\nKamera: Gabriel Beristain\nSchnitt: Scott Lerner\n\nDarsteller:\nLucas Till (Angus MacGyver)\nGeorge Eads (Jack Dalton)\nTristin Mays (Riley Davis)\nJustin Hires (Wilt Bozer)\nMeredith Eaton (Matty Webber)\nKate Bond (Jill Morgan)\nAmy Smart (Dawn)\nCory Scott Allen (Leon)\nGreg Alan Williams (Julian Halsey)",
		"ChannelName": "SAT.1",
		"Start": "2018-09-11T01:30:00+02:00",
		"Stop": "2018-09-11T02:12:08+02:00",
		"Info": {
			"Drehbuch": [
				"Andrew Karlsruher"
			],
			"Kamera": [
				"Gabriel Beristain"
			],
			"Komponist": [
				"Keith Power"
			],
			"Regie": [
				"Sharat Raju"
			],
			"Schnitt": [
				"Scott Lerner"
			]
		}
	},
	{
		"Title": "SEAL Team",
		"Subtitle": "",
		"Summary": "",
		"Description": "Die Seals vermuten, dass der afghanische Polizeikommandant Salim Hakan hinter dem Mord an ihren Kollegen steckt. Die Unterstützung ihres Vorgesetzten hält sich in Grenzen, weshalb Mandy in Eigenregie die Mission plant. Die Spur führt zu Hakans Frau, die seit Jahren verschwunden ist. Als das Team jedoch den Aufenthaltsort von Permaz Hakan herausfindet, schaltet sich eine afghanische Spezialeinheit ein. Jason weiß indes nach der Nacht mit Amy nicht, wo die beiden stehen.\n\nRegie: John Dahl\nDrehbuch: Brian Horiuchi, Sabrina Almeida\nKomponist: A. Patrick Rose\n\nDarsteller:\nDavid Boreanaz (Jason Hayes)\nMax Thieriot (Clay Spenser)\nJessica Paré (Mandy Ellis)\nNeil Brown Jr. (Ray Perry)\nA. J. Buckley (Sonny Quinn)\nJudd Lormand (Lt. Commander Eric Blackburn)\nDawn Olivieri (Amy Nelson)\nIsmail Bashey (Salim Hakan)\nNicole Shalhoub (Permaz Hakan)",
		"ChannelName": "SAT.1",
		"Start": "2018-09-11T02:12:08+02:00",
		"Stop": "2018-09-11T02:53:04+02:00",
		"Info": {
			"Drehbuch": [
				"Brian Horiuchi",
				"Sabrina Almeida"
			],
			"Komponist": [
				"A. Patrick Rose"
			],
			"Regie": [
				"John Dahl"
			]
		}
	},
	{
		"Title": "SEAL Team",
		"Subtitle": "",
		"Summary": "",
		"Description": "Mandy legt Belding die Beweise für Hakans Schuld vor, während Jason die Spitze von Steves Bohrer untersuchen lässt. Derweil besucht eine Gruppe amerikanischer Kongressabgeordneter zu Werbezwecken ein regionales Krankenhaus und das Team soll für deren Sicherheit sorgen. Doch dann verbreitet sich das Gerücht eines geplanten Anschlags. Clay macht sich indes Sorgen, dass seine Freundin fremdgeht. Lisa hat dieselben Probleme mit ihrem Freund und so schmieden die beiden einen Plan.\n\nRegie: Ruben Garcia\nDrehbuch: Valerie Armstrong, Josef Sawyer\nKomponist: A. Patrick Rose\nSchnitt: David C. Cook\n\nDarsteller:\nDavid Boreanaz (Jason Hayes)\nMax Thieriot (Clay Spenser)\nJessica Paré (Mandy Ellis)\nNeil Brown Jr. (Ray Perry)\nA. J. Buckley (Sonny Quinn)\nJudd Lormand (Lt. Commander Eric Blackburn)\nToni Trucks (Lisa Davis)\nIsmail Bashey (Salim Hakan)\nDavid DeSantos (Tim Belding)",
		"ChannelName": "SAT.1",
		"Start": "2018-09-11T02:53:04+02:00",
		"Stop": "2018-09-11T03:30:59+02:00",
		"Info": {
			"Drehbuch": [
				"Valerie Armstrong",
				"Josef Sawyer"
			],
			"Komponist": [
				"A. Patrick Rose"
			],
			"Regie": [
				"Ruben Garcia"
			],
			"Schnitt": [
				"David C. Cook"
			]
		}
	},
	{
		"Title": "Criminal Minds: Team Red",
		"Subtitle": "",
		"Summary": "",
		"Description": "In Tucson wird der 56-jährige Kenneth Richards tot in seinem Wagen gefunden. Da ihm die Augen entfernt wurden, ruft das Policedepartment die BAU hinzu. Die Profiler finden heraus, dass es sich um eine Täterin handeln muss. Als kurz darauf die Augen in einer Zeitungsbox gefunden werden, ist klar, dass die Frau eine Botschaft übermitteln will. Beth erkennt, dass sie sich auf einen Nachruf für Steve Lawford bezieht, der nach einer Knieoperation an einer Infektion gestorben ist ...\n\nRegie: Rob Spera\nDrehbuch: Chris Mundy, Edward Allen Bernero, Barry Schindel\nKomponist: Marc Fantini, Steffan Fantini, Scott Gordon\nKamera: Bing Sokolsky\nSchnitt: Janet Ashikaga\n\nDarsteller:\nForest Whitaker (Sam Cooper)\nJaneane Garofalo (Beth Griffith)\nMichael Kelly (John \"Prophet\" Sims)\nBeau Garrett (Gina LaSalle)\nMatt Ryan (Mick Rawson)\nKirsten Vangsness (Penelope Garcia)\nJustine Bateman (Margaret Mckenna)\nKaren Olivo (Vivian Solis)\nVincent Duvall (Bobby Turner)",
		"ChannelName": "SAT.1",
		"Start": "2018-09-11T03:30:59+02:00",
		"Stop": "2018-09-11T04:10:37+02:00",
		"Info": {
			"Drehbuch": [
				"Chris Mundy",
				"Edward Allen Bernero",
				"Barry Schindel"
			],
			"Kamera": [
				"Bing Sokolsky"
			],
			"Komponist": [
				"Marc Fantini",
				"Steffan Fantini",
				"Scott Gordon"
			],
			"Regie": [
				"Rob Spera"
			],
			"Schnitt": [
				"Janet Ashikaga"
			]
		}
	},
	{
		"Title": "Criminal Minds: Team Red",
		"Subtitle": "",
		"Summary": "",
		"Description": "In Chicago gibt es einen Fensterschützen, der aus großer Entfernung wahllos Menschen erschießt. Während sich die Profiler langsam ein Bild machen, mordet der Unbekannte unbehelligt weiter. Garcia stellt schließlich eine Verbindung zu einem Mord fest, der bereits zwölf Jahre zurückliegt und mit derselben Waffe verübt wurde. Die Experten gehen beim Täter von einem 25- bis 35-jährigen Mann aus, der sich - aber vor allem Mick - beweisen will, dass er der bessere Scharfschütze ist ...\n\nRegie: Terry McDonough\nDrehbuch: Chris Mundy, Edward Allen Bernero, Rob Fresco\nKomponist: Marc Fantini, Steffan Fantini, Scott Gordon\nKamera: Bing Sokolsky\nSchnitt: Lisa Bromwell\n\nDarsteller:\nForest Whitaker (Sam Cooper)\nJaneane Garofalo (Beth Griffith)\nMichael Kelly (John \"Prophet\" Sims)\nBeau Garrett (Gina LaSalle)\nMatt Ryan (Mick Rawson)\nKirsten Vangsness (Penelope Garcia)\nNoel Fisher (Jason Wheeler)\nJessica Tuck (Amy Wheeler)\nMichelle Bonilla (Nina Hernandez)",
		"ChannelName": "SAT.1",
		"Start": "2018-09-11T04:10:37+02:00",
		"Stop": "2018-09-11T04:53:09+02:00",
		"Info": {
			"Drehbuch": [
				"Chris Mundy",
				"Edward Allen Bernero",
				"Rob Fresco"
			],
			"Kamera": [
				"Bing Sokolsky"
			],
			"Komponist": [
				"Marc Fantini",
				"Steffan Fantini",
				"Scott Gordon"
			],
			"Regie": [
				"Terry McDonough"
			],
			"Schnitt": [
				"Lisa Bromwell"
			]
		}
	},
	{
		"Title": "Auf Streife",
		"Subtitle": "",
		"Summary": "",
		"Description": "Eine Familie ruft die Polizei, um eine Ruhestörung zu melden. Die Nachbarn über ihnen feiern mitten in der Woche eine wilde Party. Als die Beamten vor Ort eintreffen, erwartet sie eine Überraschung, mit der sie nicht gerechnet haben. - Ein 76-jähriger Ehemann sperrt seine Frau zu Hause ein und will sie nicht wieder gehen lassen. Was hat den Mann zu dieser Tat bewegt?",
		"ChannelName": "SAT.1",
		"Start": "2018-09-11T04:53:09+02:00",
		"Stop": "2018-09-11T05:28:53+02:00",
		"Info": {}
	},
	{
		"Title": "SAT.1-Frühstücksfernsehen",
		"Subtitle": "",
		"Summary": "",
		"Description": "Moderation: Matthias Killing, Alina Merkau\n\nMit dem \"SAT.1-Frühstücksfernsehen\" gelingt der Start in den Tag! In jeder Ausgabe werden spannende Themen behandelt, die Deutschland bewegen. Ob entspannter Talk mit interessanten Studiogästen, kontroverse Diskussionen, clevere Service-Themen oder das Neueste aus der Welt der Promis - unsere Moderatoren begleiten Sie mit viel guter Laune durch den Morgen.\n\nGast: Charlotte Karlinder, Andre Wolf, Kerstin Ott",
		"ChannelName": "SAT.1",
		"Start": "2018-09-11T05:28:53+02:00",
		"Stop": "2018-09-11T10:01:20+02:00",
		"Info": {
			"Moderation": [
				"Matthias Killing",
				"Alina Merkau"
			]
		}
	},
	{
		"Title": "Klinik am Südring",
		"Subtitle": "",
		"Summary": "",
		"Description": "Ein Tennislehrer beschuldigt seine Schülerin, ihm mit dem Schläger absichtlich die Nase gebrochen zu haben. In der Klinik bekommt das Mädchen dann plötzlich Atemprobleme.  - Eine überforderte Tagesmutter bringt eines ihrer Schützlinge mit einer blutenden Schnittwunde in die Klinik. Das Mädchen will nicht verraten, wie es zu der Verletzung gekommen ist. - Ein junger Familienvater wird nachts verletzt in die Klinik gebracht. Die Ärzte entdecken rätselhafte Fesselspuren ...",
		"ChannelName": "SAT.1",
		"Start": "2018-09-11T10:01:20+02:00",
		"Stop": "2018-09-11T10:58:55+02:00",
		"Info": {}
	},
	{
		"Title": "Im Namen der Gerechtigkeit - Wir kämpfen für Sie!",
		"Subtitle": "",
		"Summary": "",
		"Description": "Regina Holzer leidet unter Amnesie, doch sie ist davon überzeugt, eine Tochter zu haben. Allerdings hat sie keine Ahnung, wo dieses Kind ist oder wann sie es zuletzt gesehen hat. Ihr Ehemann Thomas Holzer bestreitet allerdings, dass das Paar jemals eine Tochter hatte. Da Regina keinerlei Anhaltspunkte in der Wohnung finden kann, engagiert sie Isabella Schulien, die ihre Tochter finden soll. Doch alle Recherchen laufen erst mal ins Nichts ...",
		"ChannelName": "SAT.1",
		"Start": "2018-09-11T10:58:55+02:00",
		"Stop": "2018-09-11T11:56:37+02:00",
		"Info": {}
	},
	{
		"Title": "Anwälte im Einsatz",
		"Subtitle": "",
		"Summary": "",
		"Description": "Linda Heubgen ist fassungslos: Ihr Mann will plötzlich eine \"offene Beziehung\" und holt seine 24 Jahre jüngere Freundin ins Haus. Anwalt Bernd Römer schafft es, dass Lindas Nebenbuhlerin wieder auszieht. Aber ihr Mann betrügt die 48-Jährige munter weiter. Die gehörnte Ehefrau will sich endgültig scheiden lassen. Doch dabei macht sie eine unglaubliche Entdeckung ...",
		"ChannelName": "SAT.1",
		"Start": "2018-09-11T11:56:37+02:00",
		"Stop": "2018-09-11T12:58:09+02:00",
		"Info": {}
	},
	{
		"Title": "Anwälte im Einsatz",
		"Subtitle": "",
		"Summary": "",
		"Description": "Valerie und ihr afrikanischer Freund Filip haben aus Liebe geheiratet. Dennoch steht plötzlich die Ausländerbehörde bei ihnen auf der Matte. Gegen das Paar liegt eine anonyme Anzeige wegen des Verdachts der Scheinehe vor. Hilflos müssen sie mit ansehen, wie ihre Wohnung argwöhnisch bis in den letzten Winkel inspiziert wird. Doch dann kommt Anwältin Kathrin Ruttloff dahinter wer das junge Paar auseinanderbringen will.",
		"ChannelName": "SAT.1",
		"Start": "2018-09-11T12:58:09+02:00",
		"Stop": "2018-09-11T13:59:47+02:00",
		"Info": {}
	},
	{
		"Title": "Auf Streife",
		"Subtitle": "",
		"Summary": "",
		"Description": "Ein Taxifahrer meldet einen stillen Alarm: Im gesuchten Taxi stellt sich die angebliche Fahrerin jedoch als Ex-Frau des vermissten Taxi-Fahrers heraus. - Der Chef beschuldigt seine Fahrradverkäuferin eines seiner Räder gestohlen zu haben. - Einbruch in einer Frauen-WG. Eine Bewohnerin hat dem Einbrecher die Bratpfanne übergezogen und dann die WG verlassen. - Als ein Mann in der Nachbarschaft durch einen Knallkörper verletzt wird, ist ein Zwölfjähriger im Fadenkreuz der Ermittler.",
		"ChannelName": "SAT.1",
		"Start": "2018-09-11T13:59:47+02:00",
		"Stop": "2018-09-11T14:59:01+02:00",
		"Info": {}
	},
	{
		"Title": "Auf Streife - Die Spezialisten",
		"Subtitle": "",
		"Summary": "",
		"Description": "Ein Teenager rast mit einem Auto los und fährt dabei seinen eigenen Vater auf dem Motorrad um. Lebensgefahr, denn aus dem Auto läuft brennbare Flüssigkeit aus - Ein junger Mann kommt mit Reizhusten, der keinen Auslöser zu haben scheint, in die Klinik. Eine vergessene Akupunkturnadel bringt die Spezialisten auf eine neue Spur - Ein kleiner Junge wird unter einem umgefallenen Regal begraben und liefert eine abenteuerliche Geschichte dazu ...",
		"ChannelName": "SAT.1",
		"Start": "2018-09-11T14:59:01+02:00",
		"Stop": "2018-09-11T15:55:46+02:00",
		"Info": {}
	},
	{
		"Title": "Klinik am Südring",
		"Subtitle": "",
		"Summary": "",
		"Description": "Ein Spendensammler wird überfallen und mit einer Messerstichverletzung in die Notaufnahme gebracht. Doch damit nicht genug: Bei der Behandlung entdecken die Ärzte Auffälligkeiten in seinem Darm. - Eine Kellnerin auf Rollschuhen stürzt während der Arbeit und knickt mit ihrem rechten Fuß um. Nun befürchtet sie, die Aufnahmeprüfungen zum Sportstudium zu verpassen. - Und: Ein Mann stürzt die Stufen eines Buses herunter und wird mit Gesichtsverletzungen in die Notaufnahme gebracht.",
		"ChannelName": "SAT.1",
		"Start": "2018-09-11T15:55:46+02:00",
		"Stop": "2018-09-11T16:57:43+02:00",
		"Info": {}
	},
	{
		"Title": "Klinik am Südring - Die Familienhelfer",
		"Subtitle": "",
		"Summary": "",
		"Description": "Ein fünfjähriger Junge hat im Müll der Nachbarn ein Ballett-Tutu gefunden, das er nun mit Vorliebe anzieht, auch wenn er deswegen von den anderen Kindern in der KiTa verspottet wird. Seine Eltern sind ratlos - Ein Teenie-Mädchen wird mit starken Nackenschmerzen und Übelkeit in die Klinik eingeliefert. Ist die 14-Jährige etwa schwanger? Eine Handy-Nachricht bringt den Familienhelfer auf die richtige Spur ...",
		"ChannelName": "SAT.1",
		"Start": "2018-09-11T16:57:43+02:00",
		"Stop": "2018-09-11T17:30:00+02:00",
		"Info": {}
	},
	{
		"Title": "Schicksale / oder SAT.1 Regional-Magazine",
		"Subtitle": "",
		"Summary": "",
		"Description": "In den Bundesländern Bayern, Bremen, Hamburg, Hessen, Niedersachsen, Nordrhein-Westfalen, Schleswig-Holstein sowie in Rheinland-Pfalz sehen Sie Mo-Fr von 17:30-18:00 Uhr die SAT.1 Regional-Magazine. In allen anderen Verbreitungsgebieten zeigt SAT.1 \"Schicksale - und plötzlich ist alles anders\". // Der vermisste Bruder: Als Anjas verschollener Bruder Hendrik nach einem Jahr wieder auftaucht, ist sie überglücklich. Alles scheint perfekt. Doch dann wird ihr Laden überfallen ...",
		"ChannelName": "SAT.1",
		"Start": "2018-09-11T17:30:00+02:00",
		"Stop": "2018-09-11T17:59:11+02:00",
		"Info": {}
	},
	{
		"Title": "Endlich Feierabend!",
		"Subtitle": "",
		"Summary": "",
		"Description": "Moderation: Annett Möller, Daniel Boschmann\n\n\"Endlich Feierabend!\" Annett Möller und Daniel Boschmann laden zur blauen Stunde in ihr \"Wohnzimmer\" ein. Gut informiert, gut gelaunt und gut beraten fassen sie zusammen, was Deutschland bewegt. Kontroverse Diskussionen, raffinierte Servicetipps, persönliche Schicksale sowie Geschichten hinter den Schlagzeilen des Tages: Das After-Work-Programm in SAT.1 ist bunt, immer aktuell - und garniert mit prominenten Talk-Gästen oder unterhaltsamen Studio-Aktionen.",
		"ChannelName": "SAT.1",
		"Start": "2018-09-11T17:59:11+02:00",
		"Stop": "2018-09-11T18:57:17+02:00",
		"Info": {
			"Moderation": [
				"Annett Möller",
				"Daniel Boschmann"
			]
		}
	},
	{
		"Title": "Genial daneben - Das Quiz",
		"Subtitle": "",
		"Summary": "",
		"Description": "Moderation: Hugo Egon Balder\n\nWas ist ein Trottelprivileg? Warum trägt die Braut einen Brautstrauß? Und was verbirgt sich hinter dem Begriff Lasagne-Methode? In der neuen Comedy-Quizshow \"Genial daneben - Das Quiz\" mit Hugo Egon Balder lösen Hella von Sinnen, Wigald Boning und zahlreiche Gaststars skurrile, bunte und wissenswerte Fragen des Publikums im Studio. Nur wer es schafft, die Promis aufs Glatteis zu führen, hat am Ende die Chance auf 5.000 Euro.\n\nGast: Hella von Sinnen, Wigald Boning, Lisa Feller, Rainer Calmund",
		"ChannelName": "SAT.1",
		"Start": "2018-09-11T18:57:17+02:00",
		"Stop": "2018-09-11T19:56:12+02:00",
		"Info": {
			"Moderation": [
				"Hugo Egon Balder"
			]
		}
	},
	{
		"Title": "SAT.1 Nachrichten",
		"Subtitle": "",
		"Summary": "",
		"Description": "Moderation: Marc Bator\n\n\"SAT.1 Nachrichten\" - aktuelle und kompetente Informationen live aus Berlin-Mitte. Moderiert werden die \"SAT.1 Nachrichten\" von Marc Bator, Katja Losch und Heiko Paluschka im Wechsel.",
		"ChannelName": "SAT.1",
		"Start": "2018-09-11T19:56:12+02:00",
		"Stop": "2018-09-11T20:14:37+02:00",
		"Info": {
			"Moderation": [
				"Marc Bator"
			]
		}
	},
	{
		"Title": "Seitenwechsel",
		"Subtitle": "",
		"Summary": "",
		"Description": "Turbulente Bodyswitch-Komödie mit Mina Tander und Wotan Wilke Möhring: Die Psychologin Teresa und der Fußballtrainer Alex haben nach 15 Jahren eine ernsthafte Ehekrise, sogar von Scheidung ist die Rede. Nach einem heftigen Streit mit allerlei Wünschen und Verwünschungen geschieht etwas Unfassbares: Während eines Gewitters tauschen die beiden die Körper - und das Chaos ist perfekt ...\n\nRegie: Vivian Naefe\nDrehbuch: Kati Eyssen, Andrea Sixt\nKomponist: Johannes Repka\nKamera: Hagen Bogdanski\nSchnitt: Robert Rzesacz\n\nDarsteller:\nMina Tander (Teresa Paschke)\nWotan Wilke Möhring (Alex Paschke)\nFrederick Lau (Leonard Ritter)\nAxel Stein (Moritz)\nFriederike Kempter (Rebecca)\nAnna Maria Mühe (Jenny)\nLisa Tomaschewsky (Sylvie)\nSimon Schwarz (Prof. Liebermann)\nSteve Windolf (Marc)",
		"ChannelName": "SAT.1",
		"Start": "2018-09-11T20:14:37+02:00",
		"Stop": "2018-09-11T22:21:36+02:00",
		"Info": {
			"Drehbuch": [
				"Kati Eyssen",
				"Andrea Sixt"
			],
			"Kamera": [
				"Hagen Bogdanski"
			],
			"Komponist": [
				"Johannes Repka"
			],
			"Regie": [
				"Vivian Naefe"
			],
			"Schnitt": [
				"Robert Rzesacz"
			]
		}
	},
	{
		"Title": "akte 20.18",
		"Subtitle": "",
		"Summary": "",
		"Description": "Moderation: Claus Strunz\n\nVerdrängung durch Modernisierung: Wie sicher können sich Mieter fühlen? / Tot nach Prügelei: akte-Reporter auf Spurensuche in Köthen / Traumberuf Polizist: Ist der Nachwuchs für den harten Job wirklich geeignet?",
		"ChannelName": "SAT.1",
		"Start": "2018-09-11T22:21:36+02:00",
		"Stop": "2018-09-11T23:10:00+02:00",
		"Info": {
			"Moderation": [
				"Claus Strunz"
			]
		}
	},
	{
		"Title": "Focus TV - Reportage",
		"Subtitle": "",
		"Summary": "",
		"Description": "Über 300.000 gestohlene Fahrräder - das ist die Bilanz des vergangenen Jahres. Spitzenreiter ist Berlin mit rund 70 entwendeten Drahteseln pro Tag. In Hamburg gibt es mittlerweile eine SOKO, die den Fahrraddieben mit neuen Ermittlungsmethoden und modernster Technik auf die Pelle rückt - nicht selten mit Erfolg. \"Focus TV - Reportage\" hat die Polizisten bei ihrer Arbeit begleitet.",
		"ChannelName": "SAT.1",
		"Start": "2018-09-11T23:10:00+02:00",
		"Stop": "2018-09-12T00:15:10+02:00",
		"Info": {}
	}
]